Workbook

Sheet README
A1: UniConnect — Student Portal Consolidation — Project data workbook
A2: BISY2004 Assessment 2 | Group XX | Scenario C | Fictional organisation: Southern Coast University (SCU) — fictional | Status date: Fri 25 Sep 2026
A3: Everything comes from one data file (data/project.yaml), so the WBS IDs are the same in ProjectLibre, Trello, this workbook and the diagrams. Numbers you type in are inputs; everything else is a formula.
A5: Sheet | B5: Purpose
A6: =HYPERLINK("#'Resources'!A1","Resources") -> Resources | B6: Role rates (AUD/hour) and headcount — input to all labour costs
A7: =HYPERLINK("#'Assignments'!A1","Assignments") -> Assignments | B7: Task × role × units → hours × rate = labour cost (formulas)
A8: =HYPERLINK("#'Schedule_WBS'!A1","Schedule_WBS") -> Schedule_WBS | B8: WBS work packages with ProjectLibre IDs, baseline/forecast dates, float, cost, % complete, PV/EV/AC
A9: =HYPERLINK("#'Risk_Register'!A1","Risk_Register") -> Risk_Register | B9: 13 risks, 5×5 scoring (Score = L×I), rating bands, residual risk, EMV → contingency reserve
A10: =HYPERLINK("#'Risk_Heatmap_5x5'!A1","Risk_Heatmap_5x5") -> Risk_Heatmap_5x5 | B10: Inherent and residual heat maps (COUNTIFS) with risk IDs in each cell
A11: =HYPERLINK("#'Cost_Baseline'!A1","Cost_Baseline") -> Cost_Baseline | B11: Cost by WBS branch, BAC, contingency + management reserve, total budget, monthly time-phased PV
A12: =HYPERLINK("#'EVM_Status'!A1","EVM_Status") -> EVM_Status | B12: Weekly PV/EV/AC to the status date; SV, CV, SPI, CPI, EAC (3 methods), ETC, VAC, TCPI with RAG
A13: =HYPERLINK("#'Dashboard'!A1","Dashboard") -> Dashboard | B13: KPI tiles, S-curve, risks by rating, milestone status, quality status
A14: =HYPERLINK("#'Stakeholder_Register'!A1","Stakeholder_Register") -> Stakeholder_Register | B14: Power/interest scores, quadrant formula, reason, attitude current→desired, strategy
A15: =HYPERLINK("#'Comms_Plan'!A1","Comms_Plan") -> Comms_Plan | B15: Who gets what, how, how often, owner, feedback loop
A16: =HYPERLINK("#'RACI'!A1","RACI") -> RACI | B16: Deliverables × roles with an 'exactly one A' check per row
A17: =HYPERLINK("#'Quality_Metrics'!A1","Quality_Metrics") -> Quality_Metrics | B17: Metrics, targets, current values, RAG
A18: =HYPERLINK("#'Control_Chart'!A1","Control_Chart") -> Control_Chart | B18: Defects per week with mean, UCL = mean + 3σ, LCL = max(0, mean − 3σ)
A19: =HYPERLINK("#'Change_Log'!A1","Change_Log") -> Change_Log | B19: CR-01..03 with scope/schedule/cost/risk impact and CCB decision
A20: =HYPERLINK("#'Issue_Log'!A1","Issue_Log") -> Issue_Log | B20: ISS-01..05 linked to risks, WBS, owners and actions
A21: =HYPERLINK("#'Traceability'!A1","Traceability") -> Traceability | B21: WBS → ProjectLibre ID → Trello card → cost → risks → RACI accountable → quality metric
A22: =HYPERLINK("#'Closure'!A1","Closure") -> Closure | B22: Closure checklist, benefits realisation plan, lessons learned
A23: =HYPERLINK("#'Lookups'!A1","Lookups") -> Lookups | B23: Validation lists and the 5×5 scoring scales
A25: How to read the status words
A26: Green | B26: on target (SPI/CPI 0.95 or more)
A27: Amber | B27: keep an eye on it (0.90 to 0.95)
A28: Red | B28: needs action now (under 0.90)
A29: Note | B29: No colours are used, so every rating is written as a word in the cell.

Sheet Dashboard
A1: UniConnect — Project status dashboard (status date 25 Sep 2026)
A2: Every tile is a formula that pulls from EVM_Status, Risk_Register, Issue_Log, Change_Log and Quality_Metrics.
A4: SPI | E4: CPI | I4: % complete | M4: EAC
A5: =SPI -> 0.91363262 | E5: =CPI -> 0.95727787 | I5: =EVM_Status!L18 -> 0.24642849 | M5: =EAC -> 940353.93
A8: VAC | E8: Open High risks | I8: Open issues | M8: CRs approved
A9: =VAC -> -40173.926 | E9: =Risk_Register!T21 -> 7 | I9: =Issue_Log!B11 -> 3 | M9: =COUNTIF(Change_Log!K5:K7,"Approved")&" of "&COUNTA(Change_Log!A5:A7) -> 2 of 3
A12: Overall RAG | B12: =IF(OR(SPI<0.9,CPI<0.9),"RED",IF(OR(SPI<0.95,CPI<0.95),"AMBER","GREEN")) -> AMBER | D12: ="Forecast go-live "&TEXT(E21,"dd/mm/yyyy")&" vs hard deadline 05/02/2027 — buffer "&(NETWORKDAYS(E21,DATE(2027,2,5),Holidays)-1)&" working day(s) before CR-02 recovery" -> Forecast go-live 04/02/2027 vs hard deadline 05/02/2027 — buffer 1 working day(s) before CR-02 recovery
A14: Milestones | I14: Quality metrics
A15: ID | B15: Milestone | D15: Baseline | E15: Forecast | F15: Slip (d) | G15: Status | I15: ID | J15: Metric | M15: Current | O15: RAG
A16: M1 | B16: Charter approved | D16: 46220 | E16: 46220 | F16: =IF(E16<=D16,0,NETWORKDAYS(D16,E16,Holidays)-1) -> 0 | G16: Achieved | I16: =Quality_Metrics!A5 -> Q01 | J16: =Quality_Metrics!B5 -> Migration record accuracy | M16: =Quality_Metrics!G5 -> 95.3% (trial 1) | O16: =Quality_Metrics!H5 -> Red
A17: M2 | B17: Design sign-off | D17: 46269 | E17: 46269 | F17: =IF(E17<=D17,0,NETWORKDAYS(D17,E17,Holidays)-1) -> 0 | G17: Achieved | I17: =Quality_Metrics!A6 -> Q02 | J17: =Quality_Metrics!B6 -> Portal availability | M17: =Quality_Metrics!G6 -> 99.2% (test env.) | O17: =Quality_Metrics!H6 -> Amber
A18: M3 | B18: Build complete | D18: 46321 | E18: 46321 | F18: =IF(E18<=D18,0,NETWORKDAYS(D18,E18,Holidays)-1) -> 0 | G18: =IF(F18>0,"At risk","On track") -> On track | I18: =Quality_Metrics!A7 -> Q03 | J18: =Quality_Metrics!B7 -> Page load p95 at 5,000 concurrent users | M18: =Quality_Metrics!G7 -> Not yet tested | O18: =Quality_Metrics!H7 -> Grey
A19: M4 | B19: Trial migration passed | D19: 46328 | E19: 46342 | F19: =IF(E19<=D19,0,NETWORKDAYS(D19,E19,Holidays)-1) -> 10 | G19: =IF(F19>0,"At risk","On track") -> At risk | I19: =Quality_Metrics!A8 -> Q04 | J19: =Quality_Metrics!B8 -> WCAG 2.1 AA critical failures | M19: =Quality_Metrics!G8 -> 2 (Sprint 1 scan) | O19: =Quality_Metrics!H8 -> Amber
A20: M5 | B20: UAT sign-off | D20: 46370 | E20: 46393 | F20: =IF(E20<=D20,0,NETWORKDAYS(D20,E20,Holidays)-1) -> 10 | G20: =IF(F20>0,"At risk","On track") -> At risk | I20: =Quality_Metrics!A9 -> Q05 | J20: =Quality_Metrics!B9 -> UAT pass rate | M20: =Quality_Metrics!G9 -> Not started | O20: =Quality_Metrics!H9 -> Grey
A21: M6 | B21: Go-live | D21: 46407 | E21: 46422 | F21: =IF(E21<=D21,0,NETWORKDAYS(D21,E21,Holidays)-1) -> 10 | G21: =IF(F21>0,"At risk","On track") -> At risk | I21: =Quality_Metrics!A10 -> Q06 | J21: =Quality_Metrics!B10 -> Open Severity-1 defects at go-live | M21: =Quality_Metrics!G10 -> 1 open (ISS-02) | O21: =Quality_Metrics!H10 -> Amber
A22: M7 | B22: Project closed | D22: 46457 | E22: 46471 | F22: =IF(E22<=D22,0,NETWORKDAYS(D22,E22,Holidays)-1) -> 10 | G22: =IF(F22>0,"At risk","On track") -> At risk | I22: =Quality_Metrics!A11 -> Q07 | J22: =Quality_Metrics!B11 -> Portal-related helpdesk tickets | M22: =Quality_Metrics!G11 -> Baseline 4,200/month | O22: =Quality_Metrics!H11 -> Grey
A25: Risks by rating
A26: Rating | B26: Inherent | C26: Residual
A27: Extreme | B27: =COUNTIF(Risk_Register!$I$5:$I$17,A27) -> 0 | C27: =COUNTIF(Risk_Register!$Q$5:$Q$17,A27) -> 0
A28: High | B28: =COUNTIF(Risk_Register!$I$5:$I$17,A28) -> 7 | C28: =COUNTIF(Risk_Register!$Q$5:$Q$17,A28) -> 1
A29: Medium | B29: =COUNTIF(Risk_Register!$I$5:$I$17,A29) -> 6 | C29: =COUNTIF(Risk_Register!$Q$5:$Q$17,A29) -> 7
A30: Low | B30: =COUNTIF(Risk_Register!$I$5:$I$17,A30) -> 0 | C30: =COUNTIF(Risk_Register!$Q$5:$Q$17,A30) -> 5

Sheet Risk_Register
A1: Risk register (5×5)
A2: Score = L × I; bands Low 1–4, Medium 5–9, High 10–16, Extreme 20–25; EMV = probability × cost impact
A4: ID | B4: Type | C4: Category | D4: Description (cause → event → effect) | E4: WBS links | F4: L | G4: I | H4: Score | I4: Rating | J4: Owner | K4: Strategy | L4: Response | M4: Trigger | N4: Res. L | O4: Res. I | P4: Res. score | Q4: Res. rating | R4: Probability | S4: Cost impact | T4: EMV | U4: Status | V4: Heat key | W4: Res. key
A5: R01 | B5: threat | C5: Data | D5: Because legacy SIS/portal data has duplicate and inconsistent student records (cause), trial migration may fail reconciliation (event), delaying the critical migration path and go-live (effect). | E5: 4.1, 4.2, 4.3 | F5: 4 | G5: 4 | H5: =F5*G5 -> 16 | I5: =IF(H5>=20,"Extreme",IF(H5>=10,"High",IF(H5>=5,"Medium","Low"))) -> High | J5: Data Engineer | K5: Mitigate | L5: Early data profiling in 2.1; de-duplication rules in 4.1; reconciliation scripts; contingency: cleansing mini-sprint + contractor. | M5: > 1% duplicate/unmatched records in trial migration 1 | N5: 2 | O5: 3 | P5: =N5*O5 -> 6 | Q5: =IF(P5>=20,"Extreme",IF(P5>=10,"High",IF(P5>=5,"Medium","Low"))) -> Medium | R5: =VLOOKUP(F5,ProbTable,4,FALSE()) -> 0.65 | S5: 60000 | T5: =R5*S5 -> 39000 | U5: Materialised → ISS-01 | V5: =F5&"-"&G5 -> 4-4 | W5: =N5&"-"&O5 -> 2-3
A6: R02 | B6: threat | C6: Technical/Vendor | D6: Because the LMS vendor's SSO/API support is immature (cause), SSO or LMS integration may not work (event), delaying Sprint 1 and integration APIs (effect). | E6: 2.3, 3.1, 3.5 | F6: 3 | G6: 4 | H6: =F6*G6 -> 12 | I6: =IF(H6>=20,"Extreme",IF(H6>=10,"High",IF(H6>=5,"Medium","Low"))) -> High | J6: Solution Architect | K6: Mitigate | L6: SSO proof of concept in Sprint 1; vendor SLA with escalation; weekly vendor call (C07). | M6: SSO PoC fails token exchange by end of Sprint 1 | N6: 2 | O6: 3 | P6: =N6*O6 -> 6 | Q6: =IF(P6>=20,"Extreme",IF(P6>=10,"High",IF(P6>=5,"Medium","Low"))) -> Medium | R6: =VLOOKUP(F6,ProbTable,4,FALSE()) -> 0.4 | S6: 15000 | T6: =R6*S6 -> 6000 | U6: Open — partly occurred (ISS-02) | V6: =F6&"-"&G6 -> 3-4 | W6: =N6&"-"&O6 -> 2-3
A7: R03 | B7: threat | C7: Compliance/Privacy | D7: Because migration copies identifiable student data between environments (cause), personal information could be exposed (event), causing a notifiable data breach under APP 11 (effect). | E7: 2.4, 4.2, 4.3, 4.4 | F7: 2 | G7: 5 | H7: =F7*G7 -> 10 | I7: =IF(H7>=20,"Extreme",IF(H7>=10,"High",IF(H7>=5,"Medium","Low"))) -> High | J7: Privacy Officer | K7: Mitigate | L7: PIA; masked data in non-production; encrypted transfer; access logging; MFA for all users (CR-03). | M7: Any unmasked personal data found in a non-production environment | N7: 1 | O7: 5 | P7: =N7*O7 -> 5 | Q7: =IF(P7>=20,"Extreme",IF(P7>=10,"High",IF(P7>=5,"Medium","Low"))) -> Medium | R7: =VLOOKUP(F7,ProbTable,4,FALSE()) -> 0.15 | S7: 40000 | T7: =R7*S7 -> 6000 | U7: Open | V7: =F7&"-"&G7 -> 2-5 | W7: =N7&"-"&O7 -> 1-5
A8: R04 | B8: threat | C8: Schedule | D8: Because go-live is close to Semester 1 enrolment (cause), cutover could clash with the enrolment peak (event), disrupting enrolments (effect). | E8: 4.4, 6.3 | F8: 3 | G8: 4 | H8: =F8*G8 -> 12 | I8: =IF(H8>=20,"Extreme",IF(H8>=10,"High",IF(H8>=5,"Medium","Low"))) -> High | J8: Project Manager | K8: Avoid | L8: Fixed cutover window 14–20 Jan 2027, change freeze from 1 Feb; fallback: go-live in mid-semester break with legacy portals kept live. | M8: Forecast go-live later than 29 Jan 2027 | N8: 1 | O8: 4 | P8: =N8*O8 -> 4 | Q8: =IF(P8>=20,"Extreme",IF(P8>=10,"High",IF(P8>=5,"Medium","Low"))) -> Low | R8: =VLOOKUP(F8,ProbTable,4,FALSE()) -> 0.4 | S8: 15000 | T8: =R8*S8 -> 6000 | U8: Open — watch (forecast go-live 4 Feb vs 5 Feb deadline) | V8: =F8&"-"&G8 -> 3-4 | W8: =N8&"-"&O8 -> 1-4
A9: R05 | B9: threat | C9: Resource | D9: Because developers are in high demand (cause), a key developer may resign (event), slowing sprints (effect). | E9: 3.1, 3.2, 3.3, 3.4 | F9: 2 | G9: 3 | H9: =F9*G9 -> 6 | I9: =IF(H9>=20,"Extreme",IF(H9>=10,"High",IF(H9>=5,"Medium","Low"))) -> Medium | J9: Development Lead | K9: Mitigate | L9: Pair programming, documented code, retention bonus at go-live. | M9: Resignation notice from a developer | N9: 2 | O9: 2 | P9: =N9*O9 -> 4 | Q9: =IF(P9>=20,"Extreme",IF(P9>=10,"High",IF(P9>=5,"Medium","Low"))) -> Low | R9: =VLOOKUP(F9,ProbTable,4,FALSE()) -> 0.15 | S9: 15000 | T9: =R9*S9 -> 2250 | U9: Open | V9: =F9&"-"&G9 -> 2-3 | W9: =N9&"-"&O9 -> 2-2
A10: R06 | B10: threat | C10: Scope | D10: Because faculties want their own features (cause), unapproved scope may enter sprints (event), consuming float and budget (effect). | E10: 2.2, 3.2, 3.3, 3.4 | F10: 4 | G10: 3 | H10: =F10*G10 -> 12 | I10: =IF(H10>=20,"Extreme",IF(H10>=10,"High",IF(H10>=5,"Medium","Low"))) -> High | J10: Project Manager | K10: Mitigate | L10: MoSCoW backlog; all requests through CCB (C05); Phase 2 backlog. | M10: > 2 new feature requests in a sprint | N10: 2 | O10: 3 | P10: =N10*O10 -> 6 | Q10: =IF(P10>=20,"Extreme",IF(P10>=10,"High",IF(P10>=5,"Medium","Low"))) -> Medium | R10: =VLOOKUP(F10,ProbTable,4,FALSE()) -> 0.65 | S10: 10000 | T10: =R10*S10 -> 6500 | U10: Occurred → CR-01 deferred | V10: =F10&"-"&G10 -> 4-3 | W10: =N10&"-"&O10 -> 2-3
A11: R07 | B11: threat | C11: Technical/Performance | D11: Because 5,000+ students log in at once during enrolment (cause), the portal could slow or fail (event), stopping enrolments (effect). | E11: 5.4, 6.3 | F11: 3 | G11: 5 | H11: =F11*G11 -> 15 | I11: =IF(H11>=20,"Extreme",IF(H11>=10,"High",IF(H11>=5,"Medium","Low"))) -> High | J11: Solution Architect | K11: Mitigate | L11: Load test at 5,000 concurrent users; autoscaling; CDN caching. | M11: p95 page load > 2 s in load test | N11: 2 | O11: 4 | P11: =N11*O11 -> 8 | Q11: =IF(P11>=20,"Extreme",IF(P11>=10,"High",IF(P11>=5,"Medium","Low"))) -> Medium | R11: =VLOOKUP(F11,ProbTable,4,FALSE()) -> 0.4 | S11: 15000 | T11: =R11*S11 -> 6000 | U11: Open | V11: =F11&"-"&G11 -> 3-5 | W11: =N11&"-"&O11 -> 2-4
A12: R08 | B12: threat | C12: Compliance/Accessibility | D12: Because legacy templates are not accessible (cause), the portal may fail WCAG 2.1 AA (event), excluding students with disability (effect). | E12: 2.5, 5.3 | F12: 3 | G12: 3 | H12: =F12*G12 -> 9 | I12: =IF(H12>=20,"Extreme",IF(H12>=10,"High",IF(H12>=5,"Medium","Low"))) -> Medium | J12: UX Designer | K12: Mitigate | L12: Accessible design system; automated scans each sprint; audit 5.3. | M12: Any critical failure in a sprint accessibility scan | N12: 1 | O12: 3 | P12: =N12*O12 -> 3 | Q12: =IF(P12>=20,"Extreme",IF(P12>=10,"High",IF(P12>=5,"Medium","Low"))) -> Low | R12: =VLOOKUP(F12,ProbTable,4,FALSE()) -> 0.4 | S12: 10000 | T12: =R12*S12 -> 4000 | U12: Open — ISS-04 | V12: =F12&"-"&G12 -> 3-3 | W12: =N12&"-"&O12 -> 1-3
A13: R09 | B13: threat | C13: Organisational | D13: Because students are used to the old portals (cause), adoption may be low (event), reducing benefits (effect). | E13: 6.1, 6.2 | F13: 3 | G13: 3 | H13: =F13*G13 -> 9 | I13: =IF(H13>=20,"Extreme",IF(H13>=10,"High",IF(H13>=5,"Medium","Low"))) -> Medium | J13: Change & Training Lead | K13: Mitigate | L13: SRC co-design; pilot champions; go-live campaign (C04, C08). | M13: Pilot satisfaction < 70% | N13: 2 | O13: 2 | P13: =N13*O13 -> 4 | Q13: =IF(P13>=20,"Extreme",IF(P13>=10,"High",IF(P13>=5,"Medium","Low"))) -> Low | R13: =VLOOKUP(F13,ProbTable,4,FALSE()) -> 0.4 | S13: 8000 | T13: =R13*S13 -> 3200 | U13: Open | V13: =F13&"-"&G13 -> 3-3 | W13: =N13&"-"&O13 -> 2-2
A14: R10 | B14: threat | C14: Financial | D14: Because licences are priced in USD (cause), a weaker AUD could raise licence costs (event), exceeding the cost baseline (effect). | E14: 6.3 | F14: 3 | G14: 3 | H14: =F14*G14 -> 9 | I14: =IF(H14>=20,"Extreme",IF(H14>=10,"High",IF(H14>=5,"Medium","Low"))) -> Medium | J14: Finance Office | K14: Transfer | L14: Fixed-AUD pricing clause negotiated with the vendor. | M14: AUD/USD < 0.62 before contract signature | N14: 1 | O14: 3 | P14: =N14*O14 -> 3 | Q14: =IF(P14>=20,"Extreme",IF(P14>=10,"High",IF(P14>=5,"Medium","Low"))) -> Low | R14: =VLOOKUP(F14,ProbTable,4,FALSE()) -> 0.4 | S14: 10000 | T14: =R14*S14 -> 4000 | U14: Open — fixed-AUD clause in negotiation | V14: =F14&"-"&G14 -> 3-3 | W14: =N14&"-"&O14 -> 1-3
A15: R11 | B15: threat | C15: Operational | D15: Because all students switch at once (cause), the Service Desk may be overwhelmed (event), causing long waits and complaints (effect). | E15: 6.1, 6.4 | F15: 4 | G15: 3 | H15: =F15*G15 -> 12 | I15: =IF(H15>=20,"Extreme",IF(H15>=10,"High",IF(H15>=5,"Medium","Low"))) -> High | J15: Change & Training Lead | K15: Mitigate | L15: FAQs, chatbot, surge staff roster, daily hypercare stand-up (C09). | M15: > 300 portal tickets/day during hypercare | N15: 2 | O15: 3 | P15: =N15*O15 -> 6 | Q15: =IF(P15>=20,"Extreme",IF(P15>=10,"High",IF(P15>=5,"Medium","Low"))) -> Medium | R15: =VLOOKUP(F15,ProbTable,4,FALSE()) -> 0.65 | S15: 8000 | T15: =R15*S15 -> 5200 | U15: Open | V15: =F15&"-"&G15 -> 4-3 | W15: =N15&"-"&O15 -> 2-3
A16: R12 | B16: opportunity | C16: Opportunity | D16: Because SCU already runs an identity platform (cause), SSO could reuse it (event), avoiding a separate identity licence and speeding Sprint 1 (effect). | E16: 2.3, 3.1 | F16: 3 | G16: 3 | H16: =F16*G16 -> 9 | I16: =IF(H16>=20,"Extreme",IF(H16>=10,"High",IF(H16>=5,"Medium","Low"))) -> Medium | J16: Solution Architect | K16: Exploit | L16: Design SSO on the existing platform; cancel separate IdP quote. | M16: Architecture review confirms compatibility | N16: 5 | O16: 3 | P16: =N16*O16 -> 15 | Q16: =IF(P16>=20,"Extreme",IF(P16>=10,"High",IF(P16>=5,"Medium","Low"))) -> High | R16: =VLOOKUP(F16,ProbTable,4,FALSE()) -> 0.4 | S16: -30000 | T16: =R16*S16 -> -12000 | U16: Realised in 2.3 (saving not netted from reserve) | V16: =F16&"-"&G16 -> 3-3 | W16: =N16&"-"&O16 -> 5-3
A17: R13 | B17: threat | C17: Schedule | D17: Because of the university shutdown and staff leave over summer (cause), key people may be unavailable (event), slowing the faculty pilot (effect). | E17: 6.2 | F17: 4 | G17: 2 | H17: =F17*G17 -> 8 | I17: =IF(H17>=20,"Extreme",IF(H17>=10,"High",IF(H17>=5,"Medium","Low"))) -> Medium | J17: Project Manager | K17: Accept | L17: Accepted: shutdown modelled in the ProjectLibre calendar; leave plan agreed by Oct. | M17: Leave requests overlapping 6.2 | N17: 4 | O17: 2 | P17: =N17*O17 -> 8 | Q17: =IF(P17>=20,"Extreme",IF(P17>=10,"High",IF(P17>=5,"Medium","Low"))) -> Medium | R17: =VLOOKUP(F17,ProbTable,4,FALSE()) -> 0.65 | S17: 4000 | T17: =R17*S17 -> 2600 | U17: Accepted | V17: =F17&"-"&G17 -> 4-2 | W17: =N17&"-"&O17 -> 4-2
M19: Contingency reserve (threat EMV) | T19: =SUMIF(B5:B17,"threat",T5:T17) -> 90750
M20: Opportunity EMV (not netted) | T20: =SUMIF(B5:B17,"opportunity",T5:T17) -> -12000
M21: High/Extreme risks open | T21: =COUNTIF(I5:I17,"High")+COUNTIF(I5:I17,"Extreme") -> 7

Sheet Risk_Heatmap_5x5
A1: 5×5 risk heat map (inherent and residual)
A2: Each cell counts the risks at that likelihood and impact (COUNTIFS), then shows the band and the risk IDs. Bands: 1–4 Low, 5–9 Medium, 10–16 High, 20–25 Extreme.
A4: Inherent risk (before response) | G4: Residual risk (after response)
A5: Likelihood ↓ / Impact → | B5: 1 Insignificant | C5: 2 Minor | D5: 3 Moderate | E5: 4 Major | F5: 5 Severe | G5: Likelihood ↓ / Impact → | H5: 1 Insignificant | I5: 2 Minor | J5: 3 Moderate | K5: 4 Major | L5: 5 Severe
A6: 5 Almost certain | B6: =IF(COUNTIFS(Risk_Register!$F$5:$F$17,5,Risk_Register!$G$5:$G$17,1)=0,"",COUNTIFS(Risk_Register!$F$5:$F$17,5,Risk_Register!$G$5:$G$17,1)&" · Medium"&CHAR(10)&TRIM(IF(Risk_Register!$V$5="5-1",Risk_Register!$A$5&" ","")&IF(Risk_Register!$V$6="5-1",Risk_Register!$A$6&" ","")&IF(Risk_Register!$V$7="5-1",Risk_Register!$A$7&" ","")&IF(Risk_Register!$V$8="5-1",Risk_Register!$A$8&" ","")&IF(Risk_Register!$V$9="5-1",Risk_Register!$A$9&" ","")&IF(Risk_Register!$V$10="5-1",Risk_Register!$A$10&" ","")&IF(Risk_Register!$V$11="5-1",Risk_Register!$A$11&" ","")&IF(Risk_Register!$V$12="5-1",Risk_Register!$A$12&" ","")&IF(Risk_Register!$V$13="5-1",Risk_Register!$A$13&" ","")&IF(Risk_Register!$V$14="5-1",Risk_Register!$A$14&" ","")&IF(Risk_Register!$V$15="5-1",Risk_Register!$A$15&" ","")&IF(Risk_Register!$V$16="5-1",Risk_Register!$A$16&" ","")&IF(Risk_Register!$V$17="5-1",Risk_Register!$A$17&" ",""))) | C6: =IF(COUNTIFS(Risk_Register!$F$5:$F$17,5,Risk_Register!$G$5:$G$17,2)=0,"",COUNTIFS(Risk_Register!$F$5:$F$17,5,Risk_Register!$G$5:$G$17,2)&" · High"&CHAR(10)&TRIM(IF(Risk_Register!$V$5="5-2",Risk_Register!$A$5&" ","")&IF(Risk_Register!$V$6="5-2",Risk_Register!$A$6&" ","")&IF(Risk_Register!$V$7="5-2",Risk_Register!$A$7&" ","")&IF(Risk_Register!$V$8="5-2",Risk_Register!$A$8&" ","")&IF(Risk_Register!$V$9="5-2",Risk_Register!$A$9&" ","")&IF(Risk_Register!$V$10="5-2",Risk_Register!$A$10&" ","")&IF(Risk_Register!$V$11="5-2",Risk_Register!$A$11&" ","")&IF(Risk_Register!$V$12="5-2",Risk_Register!$A$12&" ","")&IF(Risk_Register!$V$13="5-2",Risk_Register!$A$13&" ","")&IF(Risk_Register!$V$14="5-2",Risk_Register!$A$14&" ","")&IF(Risk_Register!$V$15="5-2",Risk_Register!$A$15&" ","")&IF(Risk_Register!$V$16="5-2",Risk_Register!$A$16&" ","")&IF(Risk_Register!$V$17="5-2",Risk_Register!$A$17&" ",""))) | D6: =IF(COUNTIFS(Risk_Register!$F$5:$F$17,5,Risk_Register!$G$5:$G$17,3)=0,"",COUNTIFS(Risk_Register!$F$5:$F$17,5,Risk_Register!$G$5:$G$17,3)&" · High"&CHAR(10)&TRIM(IF(Risk_Register!$V$5="5-3",Risk_Register!$A$5&" ","")&IF(Risk_Register!$V$6="5-3",Risk_Register!$A$6&" ","")&IF(Risk_Register!$V$7="5-3",Risk_Register!$A$7&" ","")&IF(Risk_Register!$V$8="5-3",Risk_Register!$A$8&" ","")&IF(Risk_Register!$V$9="5-3",Risk_Register!$A$9&" ","")&IF(Risk_Register!$V$10="5-3",Risk_Register!$A$10&" ","")&IF(Risk_Register!$V$11="5-3",Risk_Register!$A$11&" ","")&IF(Risk_Register!$V$12="5-3",Risk_Register!$A$12&" ","")&IF(Risk_Register!$V$13="5-3",Risk_Register!$A$13&" ","")&IF(Risk_Register!$V$14="5-3",Risk_Register!$A$14&" ","")&IF(Risk_Register!$V$15="5-3",Risk_Register!$A$15&" ","")&IF(Risk_Register!$V$16="5-3",Risk_Register!$A$16&" ","")&IF(Risk_Register!$V$17="5-3",Risk_Register!$A$17&" ",""))) | E6: =IF(COUNTIFS(Risk_Register!$F$5:$F$17,5,Risk_Register!$G$5:$G$17,4)=0,"",COUNTIFS(Risk_Register!$F$5:$F$17,5,Risk_Register!$G$5:$G$17,4)&" · Extreme"&CHAR(10)&TRIM(IF(Risk_Register!$V$5="5-4",Risk_Register!$A$5&" ","")&IF(Risk_Register!$V$6="5-4",Risk_Register!$A$6&" ","")&IF(Risk_Register!$V$7="5-4",Risk_Register!$A$7&" ","")&IF(Risk_Register!$V$8="5-4",Risk_Register!$A$8&" ","")&IF(Risk_Register!$V$9="5-4",Risk_Register!$A$9&" ","")&IF(Risk_Register!$V$10="5-4",Risk_Register!$A$10&" ","")&IF(Risk_Register!$V$11="5-4",Risk_Register!$A$11&" ","")&IF(Risk_Register!$V$12="5-4",Risk_Register!$A$12&" ","")&IF(Risk_Register!$V$13="5-4",Risk_Register!$A$13&" ","")&IF(Risk_Register!$V$14="5-4",Risk_Register!$A$14&" ","")&IF(Risk_Register!$V$15="5-4",Risk_Register!$A$15&" ","")&IF(Risk_Register!$V$16="5-4",Risk_Register!$A$16&" ","")&IF(Risk_Register!$V$17="5-4",Risk_Register!$A$17&" ",""))) | F6: =IF(COUNTIFS(Risk_Register!$F$5:$F$17,5,Risk_Register!$G$5:$G$17,5)=0,"",COUNTIFS(Risk_Register!$F$5:$F$17,5,Risk_Register!$G$5:$G$17,5)&" · Extreme"&CHAR(10)&TRIM(IF(Risk_Register!$V$5="5-5",Risk_Register!$A$5&" ","")&IF(Risk_Register!$V$6="5-5",Risk_Register!$A$6&" ","")&IF(Risk_Register!$V$7="5-5",Risk_Register!$A$7&" ","")&IF(Risk_Register!$V$8="5-5",Risk_Register!$A$8&" ","")&IF(Risk_Register!$V$9="5-5",Risk_Register!$A$9&" ","")&IF(Risk_Register!$V$10="5-5",Risk_Register!$A$10&" ","")&IF(Risk_Register!$V$11="5-5",Risk_Register!$A$11&" ","")&IF(Risk_Register!$V$12="5-5",Risk_Register!$A$12&" ","")&IF(Risk_Register!$V$13="5-5",Risk_Register!$A$13&" ","")&IF(Risk_Register!$V$14="5-5",Risk_Register!$A$14&" ","")&IF(Risk_Register!$V$15="5-5",Risk_Register!$A$15&" ","")&IF(Risk_Register!$V$16="5-5",Risk_Register!$A$16&" ","")&IF(Risk_Register!$V$17="5-5",Risk_Register!$A$17&" ",""))) | G6: 5 Almost certain | H6: =IF(COUNTIFS(Risk_Register!$N$5:$N$17,5,Risk_Register!$O$5:$O$17,1)=0,"",COUNTIFS(Risk_Register!$N$5:$N$17,5,Risk_Register!$O$5:$O$17,1)&" · Medium"&CHAR(10)&TRIM(IF(Risk_Register!$W$5="5-1",Risk_Register!$A$5&" ","")&IF(Risk_Register!$W$6="5-1",Risk_Register!$A$6&" ","")&IF(Risk_Register!$W$7="5-1",Risk_Register!$A$7&" ","")&IF(Risk_Register!$W$8="5-1",Risk_Register!$A$8&" ","")&IF(Risk_Register!$W$9="5-1",Risk_Register!$A$9&" ","")&IF(Risk_Register!$W$10="5-1",Risk_Register!$A$10&" ","")&IF(Risk_Register!$W$11="5-1",Risk_Register!$A$11&" ","")&IF(Risk_Register!$W$12="5-1",Risk_Register!$A$12&" ","")&IF(Risk_Register!$W$13="5-1",Risk_Register!$A$13&" ","")&IF(Risk_Register!$W$14="5-1",Risk_Register!$A$14&" ","")&IF(Risk_Register!$W$15="5-1",Risk_Register!$A$15&" ","")&IF(Risk_Register!$W$16="5-1",Risk_Register!$A$16&" ","")&IF(Risk_Register!$W$17="5-1",Risk_Register!$A$17&" ",""))) | I6: =IF(COUNTIFS(Risk_Register!$N$5:$N$17,5,Risk_Register!$O$5:$O$17,2)=0,"",COUNTIFS(Risk_Register!$N$5:$N$17,5,Risk_Register!$O$5:$O$17,2)&" · High"&CHAR(10)&TRIM(IF(Risk_Register!$W$5="5-2",Risk_Register!$A$5&" ","")&IF(Risk_Register!$W$6="5-2",Risk_Register!$A$6&" ","")&IF(Risk_Register!$W$7="5-2",Risk_Register!$A$7&" ","")&IF(Risk_Register!$W$8="5-2",Risk_Register!$A$8&" ","")&IF(Risk_Register!$W$9="5-2",Risk_Register!$A$9&" ","")&IF(Risk_Register!$W$10="5-2",Risk_Register!$A$10&" ","")&IF(Risk_Register!$W$11="5-2",Risk_Register!$A$11&" ","")&IF(Risk_Register!$W$12="5-2",Risk_Register!$A$12&" ","")&IF(Risk_Register!$W$13="5-2",Risk_Register!$A$13&" ","")&IF(Risk_Register!$W$14="5-2",Risk_Register!$A$14&" ","")&IF(Risk_Register!$W$15="5-2",Risk_Register!$A$15&" ","")&IF(Risk_Register!$W$16="5-2",Risk_Register!$A$16&" ","")&IF(Risk_Register!$W$17="5-2",Risk_Register!$A$17&" ",""))) | J6: =IF(COUNTIFS(Risk_Register!$N$5:$N$17,5,Risk_Register!$O$5:$O$17,3)=0,"",COUNTIFS(Risk_Register!$N$5:$N$17,5,Risk_Register!$O$5:$O$17,3)&" · High"&CHAR(10)&TRIM(IF(Risk_Register!$W$5="5-3",Risk_Register!$A$5&" ","")&IF(Risk_Register!$W$6="5-3",Risk_Register!$A$6&" ","")&IF(Risk_Register!$W$7="5-3",Risk_Register!$A$7&" ","")&IF(Risk_Register!$W$8="5-3",Risk_Register!$A$8&" ","")&IF(Risk_Register!$W$9="5-3",Risk_Register!$A$9&" ","")&IF(Risk_Register!$W$10="5-3",Risk_Register!$A$10&" ","")&IF(Risk_Register!$W$11="5-3",Risk_Register!$A$11&" ","")&IF(Risk_Register!$W$12="5-3",Risk_Register!$A$12&" ","")&IF(Risk_Register!$W$13="5-3",Risk_Register!$A$13&" ","")&IF(Risk_Register!$W$14="5-3",Risk_Register!$A$14&" ","")&IF(Risk_Register!$W$15="5-3",Risk_Register!$A$15&" ","")&IF(Risk_Register!$W$16="5-3",Risk_Register!$A$16&" ","")&IF(Risk_Register!$W$17="5-3",Risk_Register!$A$17&" ",""))) -> 1 · High R12 | K6: =IF(COUNTIFS(Risk_Register!$N$5:$N$17,5,Risk_Register!$O$5:$O$17,4)=0,"",COUNTIFS(Risk_Register!$N$5:$N$17,5,Risk_Register!$O$5:$O$17,4)&" · Extreme"&CHAR(10)&TRIM(IF(Risk_Register!$W$5="5-4",Risk_Register!$A$5&" ","")&IF(Risk_Register!$W$6="5-4",Risk_Register!$A$6&" ","")&IF(Risk_Register!$W$7="5-4",Risk_Register!$A$7&" ","")&IF(Risk_Register!$W$8="5-4",Risk_Register!$A$8&" ","")&IF(Risk_Register!$W$9="5-4",Risk_Register!$A$9&" ","")&IF(Risk_Register!$W$10="5-4",Risk_Register!$A$10&" ","")&IF(Risk_Register!$W$11="5-4",Risk_Register!$A$11&" ","")&IF(Risk_Register!$W$12="5-4",Risk_Register!$A$12&" ","")&IF(Risk_Register!$W$13="5-4",Risk_Register!$A$13&" ","")&IF(Risk_Register!$W$14="5-4",Risk_Register!$A$14&" ","")&IF(Risk_Register!$W$15="5-4",Risk_Register!$A$15&" ","")&IF(Risk_Register!$W$16="5-4",Risk_Register!$A$16&" ","")&IF(Risk_Register!$W$17="5-4",Risk_Register!$A$17&" ",""))) | L6: =IF(COUNTIFS(Risk_Register!$N$5:$N$17,5,Risk_Register!$O$5:$O$17,5)=0,"",COUNTIFS(Risk_Register!$N$5:$N$17,5,Risk_Register!$O$5:$O$17,5)&" · Extreme"&CHAR(10)&TRIM(IF(Risk_Register!$W$5="5-5",Risk_Register!$A$5&" ","")&IF(Risk_Register!$W$6="5-5",Risk_Register!$A$6&" ","")&IF(Risk_Register!$W$7="5-5",Risk_Register!$A$7&" ","")&IF(Risk_Register!$W$8="5-5",Risk_Register!$A$8&" ","")&IF(Risk_Register!$W$9="5-5",Risk_Register!$A$9&" ","")&IF(Risk_Register!$W$10="5-5",Risk_Register!$A$10&" ","")&IF(Risk_Register!$W$11="5-5",Risk_Register!$A$11&" ","")&IF(Risk_Register!$W$12="5-5",Risk_Register!$A$12&" ","")&IF(Risk_Register!$W$13="5-5",Risk_Register!$A$13&" ","")&IF(Risk_Register!$W$14="5-5",Risk_Register!$A$14&" ","")&IF(Risk_Register!$W$15="5-5",Risk_Register!$A$15&" ","")&IF(Risk_Register!$W$16="5-5",Risk_Register!$A$16&" ","")&IF(Risk_Register!$W$17="5-5",Risk_Register!$A$17&" ","")))
A7: 4 Likely | B7: =IF(COUNTIFS(Risk_Register!$F$5:$F$17,4,Risk_Register!$G$5:$G$17,1)=0,"",COUNTIFS(Risk_Register!$F$5:$F$17,4,Risk_Register!$G$5:$G$17,1)&" · Low"&CHAR(10)&TRIM(IF(Risk_Register!$V$5="4-1",Risk_Register!$A$5&" ","")&IF(Risk_Register!$V$6="4-1",Risk_Register!$A$6&" ","")&IF(Risk_Register!$V$7="4-1",Risk_Register!$A$7&" ","")&IF(Risk_Register!$V$8="4-1",Risk_Register!$A$8&" ","")&IF(Risk_Register!$V$9="4-1",Risk_Register!$A$9&" ","")&IF(Risk_Register!$V$10="4-1",Risk_Register!$A$10&" ","")&IF(Risk_Register!$V$11="4-1",Risk_Register!$A$11&" ","")&IF(Risk_Register!$V$12="4-1",Risk_Register!$A$12&" ","")&IF(Risk_Register!$V$13="4-1",Risk_Register!$A$13&" ","")&IF(Risk_Register!$V$14="4-1",Risk_Register!$A$14&" ","")&IF(Risk_Register!$V$15="4-1",Risk_Register!$A$15&" ","")&IF(Risk_Register!$V$16="4-1",Risk_Register!$A$16&" ","")&IF(Risk_Register!$V$17="4-1",Risk_Register!$A$17&" ",""))) | C7: =IF(COUNTIFS(Risk_Register!$F$5:$F$17,4,Risk_Register!$G$5:$G$17,2)=0,"",COUNTIFS(Risk_Register!$F$5:$F$17,4,Risk_Register!$G$5:$G$17,2)&" · Medium"&CHAR(10)&TRIM(IF(Risk_Register!$V$5="4-2",Risk_Register!$A$5&" ","")&IF(Risk_Register!$V$6="4-2",Risk_Register!$A$6&" ","")&IF(Risk_Register!$V$7="4-2",Risk_Register!$A$7&" ","")&IF(Risk_Register!$V$8="4-2",Risk_Register!$A$8&" ","")&IF(Risk_Register!$V$9="4-2",Risk_Register!$A$9&" ","")&IF(Risk_Register!$V$10="4-2",Risk_Register!$A$10&" ","")&IF(Risk_Register!$V$11="4-2",Risk_Register!$A$11&" ","")&IF(Risk_Register!$V$12="4-2",Risk_Register!$A$12&" ","")&IF(Risk_Register!$V$13="4-2",Risk_Register!$A$13&" ","")&IF(Risk_Register!$V$14="4-2",Risk_Register!$A$14&" ","")&IF(Risk_Register!$V$15="4-2",Risk_Register!$A$15&" ","")&IF(Risk_Register!$V$16="4-2",Risk_Register!$A$16&" ","")&IF(Risk_Register!$V$17="4-2",Risk_Register!$A$17&" ",""))) -> 1 · Medium R13 | D7: =IF(COUNTIFS(Risk_Register!$F$5:$F$17,4,Risk_Register!$G$5:$G$17,3)=0,"",COUNTIFS(Risk_Register!$F$5:$F$17,4,Risk_Register!$G$5:$G$17,3)&" · High"&CHAR(10)&TRIM(IF(Risk_Register!$V$5="4-3",Risk_Register!$A$5&" ","")&IF(Risk_Register!$V$6="4-3",Risk_Register!$A$6&" ","")&IF(Risk_Register!$V$7="4-3",Risk_Register!$A$7&" ","")&IF(Risk_Register!$V$8="4-3",Risk_Register!$A$8&" ","")&IF(Risk_Register!$V$9="4-3",Risk_Register!$A$9&" ","")&IF(Risk_Register!$V$10="4-3",Risk_Register!$A$10&" ","")&IF(Risk_Register!$V$11="4-3",Risk_Register!$A$11&" ","")&IF(Risk_Register!$V$12="4-3",Risk_Register!$A$12&" ","")&IF(Risk_Register!$V$13="4-3",Risk_Register!$A$13&" ","")&IF(Risk_Register!$V$14="4-3",Risk_Register!$A$14&" ","")&IF(Risk_Register!$V$15="4-3",Risk_Register!$A$15&" ","")&IF(Risk_Register!$V$16="4-3",Risk_Register!$A$16&" ","")&IF(Risk_Register!$V$17="4-3",Risk_Register!$A$17&" ",""))) -> 2 · High R06 R11 | E7: =IF(COUNTIFS(Risk_Register!$F$5:$F$17,4,Risk_Register!$G$5:$G$17,4)=0,"",COUNTIFS(Risk_Register!$F$5:$F$17,4,Risk_Register!$G$5:$G$17,4)&" · High"&CHAR(10)&TRIM(IF(Risk_Register!$V$5="4-4",Risk_Register!$A$5&" ","")&IF(Risk_Register!$V$6="4-4",Risk_Register!$A$6&" ","")&IF(Risk_Register!$V$7="4-4",Risk_Register!$A$7&" ","")&IF(Risk_Register!$V$8="4-4",Risk_Register!$A$8&" ","")&IF(Risk_Register!$V$9="4-4",Risk_Register!$A$9&" ","")&IF(Risk_Register!$V$10="4-4",Risk_Register!$A$10&" ","")&IF(Risk_Register!$V$11="4-4",Risk_Register!$A$11&" ","")&IF(Risk_Register!$V$12="4-4",Risk_Register!$A$12&" ","")&IF(Risk_Register!$V$13="4-4",Risk_Register!$A$13&" ","")&IF(Risk_Register!$V$14="4-4",Risk_Register!$A$14&" ","")&IF(Risk_Register!$V$15="4-4",Risk_Register!$A$15&" ","")&IF(Risk_Register!$V$16="4-4",Risk_Register!$A$16&" ","")&IF(Risk_Register!$V$17="4-4",Risk_Register!$A$17&" ",""))) -> 1 · High R01 | F7: =IF(COUNTIFS(Risk_Register!$F$5:$F$17,4,Risk_Register!$G$5:$G$17,5)=0,"",COUNTIFS(Risk_Register!$F$5:$F$17,4,Risk_Register!$G$5:$G$17,5)&" · Extreme"&CHAR(10)&TRIM(IF(Risk_Register!$V$5="4-5",Risk_Register!$A$5&" ","")&IF(Risk_Register!$V$6="4-5",Risk_Register!$A$6&" ","")&IF(Risk_Register!$V$7="4-5",Risk_Register!$A$7&" ","")&IF(Risk_Register!$V$8="4-5",Risk_Register!$A$8&" ","")&IF(Risk_Register!$V$9="4-5",Risk_Register!$A$9&" ","")&IF(Risk_Register!$V$10="4-5",Risk_Register!$A$10&" ","")&IF(Risk_Register!$V$11="4-5",Risk_Register!$A$11&" ","")&IF(Risk_Register!$V$12="4-5",Risk_Register!$A$12&" ","")&IF(Risk_Register!$V$13="4-5",Risk_Register!$A$13&" ","")&IF(Risk_Register!$V$14="4-5",Risk_Register!$A$14&" ","")&IF(Risk_Register!$V$15="4-5",Risk_Register!$A$15&" ","")&IF(Risk_Register!$V$16="4-5",Risk_Register!$A$16&" ","")&IF(Risk_Register!$V$17="4-5",Risk_Register!$A$17&" ",""))) | G7: 4 Likely | H7: =IF(COUNTIFS(Risk_Register!$N$5:$N$17,4,Risk_Register!$O$5:$O$17,1)=0,"",COUNTIFS(Risk_Register!$N$5:$N$17,4,Risk_Register!$O$5:$O$17,1)&" · Low"&CHAR(10)&TRIM(IF(Risk_Register!$W$5="4-1",Risk_Register!$A$5&" ","")&IF(Risk_Register!$W$6="4-1",Risk_Register!$A$6&" ","")&IF(Risk_Register!$W$7="4-1",Risk_Register!$A$7&" ","")&IF(Risk_Register!$W$8="4-1",Risk_Register!$A$8&" ","")&IF(Risk_Register!$W$9="4-1",Risk_Register!$A$9&" ","")&IF(Risk_Register!$W$10="4-1",Risk_Register!$A$10&" ","")&IF(Risk_Register!$W$11="4-1",Risk_Register!$A$11&" ","")&IF(Risk_Register!$W$12="4-1",Risk_Register!$A$12&" ","")&IF(Risk_Register!$W$13="4-1",Risk_Register!$A$13&" ","")&IF(Risk_Register!$W$14="4-1",Risk_Register!$A$14&" ","")&IF(Risk_Register!$W$15="4-1",Risk_Register!$A$15&" ","")&IF(Risk_Register!$W$16="4-1",Risk_Register!$A$16&" ","")&IF(Risk_Register!$W$17="4-1",Risk_Register!$A$17&" ",""))) | I7: =IF(COUNTIFS(Risk_Register!$N$5:$N$17,4,Risk_Register!$O$5:$O$17,2)=0,"",COUNTIFS(Risk_Register!$N$5:$N$17,4,Risk_Register!$O$5:$O$17,2)&" · Medium"&CHAR(10)&TRIM(IF(Risk_Register!$W$5="4-2",Risk_Register!$A$5&" ","")&IF(Risk_Register!$W$6="4-2",Risk_Register!$A$6&" ","")&IF(Risk_Register!$W$7="4-2",Risk_Register!$A$7&" ","")&IF(Risk_Register!$W$8="4-2",Risk_Register!$A$8&" ","")&IF(Risk_Register!$W$9="4-2",Risk_Register!$A$9&" ","")&IF(Risk_Register!$W$10="4-2",Risk_Register!$A$10&" ","")&IF(Risk_Register!$W$11="4-2",Risk_Register!$A$11&" ","")&IF(Risk_Register!$W$12="4-2",Risk_Register!$A$12&" ","")&IF(Risk_Register!$W$13="4-2",Risk_Register!$A$13&" ","")&IF(Risk_Register!$W$14="4-2",Risk_Register!$A$14&" ","")&IF(Risk_Register!$W$15="4-2",Risk_Register!$A$15&" ","")&IF(Risk_Register!$W$16="4-2",Risk_Register!$A$16&" ","")&IF(Risk_Register!$W$17="4-2",Risk_Register!$A$17&" ",""))) -> 1 · Medium R13 | J7: =IF(COUNTIFS(Risk_Register!$N$5:$N$17,4,Risk_Register!$O$5:$O$17,3)=0,"",COUNTIFS(Risk_Register!$N$5:$N$17,4,Risk_Register!$O$5:$O$17,3)&" · High"&CHAR(10)&TRIM(IF(Risk_Register!$W$5="4-3",Risk_Register!$A$5&" ","")&IF(Risk_Register!$W$6="4-3",Risk_Register!$A$6&" ","")&IF(Risk_Register!$W$7="4-3",Risk_Register!$A$7&" ","")&IF(Risk_Register!$W$8="4-3",Risk_Register!$A$8&" ","")&IF(Risk_Register!$W$9="4-3",Risk_Register!$A$9&" ","")&IF(Risk_Register!$W$10="4-3",Risk_Register!$A$10&" ","")&IF(Risk_Register!$W$11="4-3",Risk_Register!$A$11&" ","")&IF(Risk_Register!$W$12="4-3",Risk_Register!$A$12&" ","")&IF(Risk_Register!$W$13="4-3",Risk_Register!$A$13&" ","")&IF(Risk_Register!$W$14="4-3",Risk_Register!$A$14&" ","")&IF(Risk_Register!$W$15="4-3",Risk_Register!$A$15&" ","")&IF(Risk_Register!$W$16="4-3",Risk_Register!$A$16&" ","")&IF(Risk_Register!$W$17="4-3",Risk_Register!$A$17&" ",""))) | K7: =IF(COUNTIFS(Risk_Register!$N$5:$N$17,4,Risk_Register!$O$5:$O$17,4)=0,"",COUNTIFS(Risk_Register!$N$5:$N$17,4,Risk_Register!$O$5:$O$17,4)&" · High"&CHAR(10)&TRIM(IF(Risk_Register!$W$5="4-4",Risk_Register!$A$5&" ","")&IF(Risk_Register!$W$6="4-4",Risk_Register!$A$6&" ","")&IF(Risk_Register!$W$7="4-4",Risk_Register!$A$7&" ","")&IF(Risk_Register!$W$8="4-4",Risk_Register!$A$8&" ","")&IF(Risk_Register!$W$9="4-4",Risk_Register!$A$9&" ","")&IF(Risk_Register!$W$10="4-4",Risk_Register!$A$10&" ","")&IF(Risk_Register!$W$11="4-4",Risk_Register!$A$11&" ","")&IF(Risk_Register!$W$12="4-4",Risk_Register!$A$12&" ","")&IF(Risk_Register!$W$13="4-4",Risk_Register!$A$13&" ","")&IF(Risk_Register!$W$14="4-4",Risk_Register!$A$14&" ","")&IF(Risk_Register!$W$15="4-4",Risk_Register!$A$15&" ","")&IF(Risk_Register!$W$16="4-4",Risk_Register!$A$16&" ","")&IF(Risk_Register!$W$17="4-4",Risk_Register!$A$17&" ",""))) | L7: =IF(COUNTIFS(Risk_Register!$N$5:$N$17,4,Risk_Register!$O$5:$O$17,5)=0,"",COUNTIFS(Risk_Register!$N$5:$N$17,4,Risk_Register!$O$5:$O$17,5)&" · Extreme"&CHAR(10)&TRIM(IF(Risk_Register!$W$5="4-5",Risk_Register!$A$5&" ","")&IF(Risk_Register!$W$6="4-5",Risk_Register!$A$6&" ","")&IF(Risk_Register!$W$7="4-5",Risk_Register!$A$7&" ","")&IF(Risk_Register!$W$8="4-5",Risk_Register!$A$8&" ","")&IF(Risk_Register!$W$9="4-5",Risk_Register!$A$9&" ","")&IF(Risk_Register!$W$10="4-5",Risk_Register!$A$10&" ","")&IF(Risk_Register!$W$11="4-5",Risk_Register!$A$11&" ","")&IF(Risk_Register!$W$12="4-5",Risk_Register!$A$12&" ","")&IF(Risk_Register!$W$13="4-5",Risk_Register!$A$13&" ","")&IF(Risk_Register!$W$14="4-5",Risk_Register!$A$14&" ","")&IF(Risk_Register!$W$15="4-5",Risk_Register!$A$15&" ","")&IF(Risk_Register!$W$16="4-5",Risk_Register!$A$16&" ","")&IF(Risk_Register!$W$17="4-5",Risk_Register!$A$17&" ","")))
A8: 3 Possible | B8: =IF(COUNTIFS(Risk_Register!$F$5:$F$17,3,Risk_Register!$G$5:$G$17,1)=0,"",COUNTIFS(Risk_Register!$F$5:$F$17,3,Risk_Register!$G$5:$G$17,1)&" · Low"&CHAR(10)&TRIM(IF(Risk_Register!$V$5="3-1",Risk_Register!$A$5&" ","")&IF(Risk_Register!$V$6="3-1",Risk_Register!$A$6&" ","")&IF(Risk_Register!$V$7="3-1",Risk_Register!$A$7&" ","")&IF(Risk_Register!$V$8="3-1",Risk_Register!$A$8&" ","")&IF(Risk_Register!$V$9="3-1",Risk_Register!$A$9&" ","")&IF(Risk_Register!$V$10="3-1",Risk_Register!$A$10&" ","")&IF(Risk_Register!$V$11="3-1",Risk_Register!$A$11&" ","")&IF(Risk_Register!$V$12="3-1",Risk_Register!$A$12&" ","")&IF(Risk_Register!$V$13="3-1",Risk_Register!$A$13&" ","")&IF(Risk_Register!$V$14="3-1",Risk_Register!$A$14&" ","")&IF(Risk_Register!$V$15="3-1",Risk_Register!$A$15&" ","")&IF(Risk_Register!$V$16="3-1",Risk_Register!$A$16&" ","")&IF(Risk_Register!$V$17="3-1",Risk_Register!$A$17&" ",""))) | C8: =IF(COUNTIFS(Risk_Register!$F$5:$F$17,3,Risk_Register!$G$5:$G$17,2)=0,"",COUNTIFS(Risk_Register!$F$5:$F$17,3,Risk_Register!$G$5:$G$17,2)&" · Medium"&CHAR(10)&TRIM(IF(Risk_Register!$V$5="3-2",Risk_Register!$A$5&" ","")&IF(Risk_Register!$V$6="3-2",Risk_Register!$A$6&" ","")&IF(Risk_Register!$V$7="3-2",Risk_Register!$A$7&" ","")&IF(Risk_Register!$V$8="3-2",Risk_Register!$A$8&" ","")&IF(Risk_Register!$V$9="3-2",Risk_Register!$A$9&" ","")&IF(Risk_Register!$V$10="3-2",Risk_Register!$A$10&" ","")&IF(Risk_Register!$V$11="3-2",Risk_Register!$A$11&" ","")&IF(Risk_Register!$V$12="3-2",Risk_Register!$A$12&" ","")&IF(Risk_Register!$V$13="3-2",Risk_Register!$A$13&" ","")&IF(Risk_Register!$V$14="3-2",Risk_Register!$A$14&" ","")&IF(Risk_Register!$V$15="3-2",Risk_Register!$A$15&" ","")&IF(Risk_Register!$V$16="3-2",Risk_Register!$A$16&" ","")&IF(Risk_Register!$V$17="3-2",Risk_Register!$A$17&" ",""))) | D8: =IF(COUNTIFS(Risk_Register!$F$5:$F$17,3,Risk_Register!$G$5:$G$17,3)=0,"",COUNTIFS(Risk_Register!$F$5:$F$17,3,Risk_Register!$G$5:$G$17,3)&" · Medium"&CHAR(10)&TRIM(IF(Risk_Register!$V$5="3-3",Risk_Register!$A$5&" ","")&IF(Risk_Register!$V$6="3-3",Risk_Register!$A$6&" ","")&IF(Risk_Register!$V$7="3-3",Risk_Register!$A$7&" ","")&IF(Risk_Register!$V$8="3-3",Risk_Register!$A$8&" ","")&IF(Risk_Register!$V$9="3-3",Risk_Register!$A$9&" ","")&IF(Risk_Register!$V$10="3-3",Risk_Register!$A$10&" ","")&IF(Risk_Register!$V$11="3-3",Risk_Register!$A$11&" ","")&IF(Risk_Register!$V$12="3-3",Risk_Register!$A$12&" ","")&IF(Risk_Register!$V$13="3-3",Risk_Register!$A$13&" ","")&IF(Risk_Register!$V$14="3-3",Risk_Register!$A$14&" ","")&IF(Risk_Register!$V$15="3-3",Risk_Register!$A$15&" ","")&IF(Risk_Register!$V$16="3-3",Risk_Register!$A$16&" ","")&IF(Risk_Register!$V$17="3-3",Risk_Register!$A$17&" ",""))) -> 4 · Medium R08 R09 R10 R12 | E8: =IF(COUNTIFS(Risk_Register!$F$5:$F$17,3,Risk_Register!$G$5:$G$17,4)=0,"",COUNTIFS(Risk_Register!$F$5:$F$17,3,Risk_Register!$G$5:$G$17,4)&" · High"&CHAR(10)&TRIM(IF(Risk_Register!$V$5="3-4",Risk_Register!$A$5&" ","")&IF(Risk_Register!$V$6="3-4",Risk_Register!$A$6&" ","")&IF(Risk_Register!$V$7="3-4",Risk_Register!$A$7&" ","")&IF(Risk_Register!$V$8="3-4",Risk_Register!$A$8&" ","")&IF(Risk_Register!$V$9="3-4",Risk_Register!$A$9&" ","")&IF(Risk_Register!$V$10="3-4",Risk_Register!$A$10&" ","")&IF(Risk_Register!$V$11="3-4",Risk_Register!$A$11&" ","")&IF(Risk_Register!$V$12="3-4",Risk_Register!$A$12&" ","")&IF(Risk_Register!$V$13="3-4",Risk_Register!$A$13&" ","")&IF(Risk_Register!$V$14="3-4",Risk_Register!$A$14&" ","")&IF(Risk_Register!$V$15="3-4",Risk_Register!$A$15&" ","")&IF(Risk_Register!$V$16="3-4",Risk_Register!$A$16&" ","")&IF(Risk_Register!$V$17="3-4",Risk_Register!$A$17&" ",""))) -> 2 · High R02 R04 | F8: =IF(COUNTIFS(Risk_Register!$F$5:$F$17,3,Risk_Register!$G$5:$G$17,5)=0,"",COUNTIFS(Risk_Register!$F$5:$F$17,3,Risk_Register!$G$5:$G$17,5)&" · High"&CHAR(10)&TRIM(IF(Risk_Register!$V$5="3-5",Risk_Register!$A$5&" ","")&IF(Risk_Register!$V$6="3-5",Risk_Register!$A$6&" ","")&IF(Risk_Register!$V$7="3-5",Risk_Register!$A$7&" ","")&IF(Risk_Register!$V$8="3-5",Risk_Register!$A$8&" ","")&IF(Risk_Register!$V$9="3-5",Risk_Register!$A$9&" ","")&IF(Risk_Register!$V$10="3-5",Risk_Register!$A$10&" ","")&IF(Risk_Register!$V$11="3-5",Risk_Register!$A$11&" ","")&IF(Risk_Register!$V$12="3-5",Risk_Register!$A$12&" ","")&IF(Risk_Register!$V$13="3-5",Risk_Register!$A$13&" ","")&IF(Risk_Register!$V$14="3-5",Risk_Register!$A$14&" ","")&IF(Risk_Register!$V$15="3-5",Risk_Register!$A$15&" ","")&IF(Risk_Register!$V$16="3-5",Risk_Register!$A$16&" ","")&IF(Risk_Register!$V$17="3-5",Risk_Register!$A$17&" ",""))) -> 1 · High R07 | G8: 3 Possible | H8: =IF(COUNTIFS(Risk_Register!$N$5:$N$17,3,Risk_Register!$O$5:$O$17,1)=0,"",COUNTIFS(Risk_Register!$N$5:$N$17,3,Risk_Register!$O$5:$O$17,1)&" · Low"&CHAR(10)&TRIM(IF(Risk_Register!$W$5="3-1",Risk_Register!$A$5&" ","")&IF(Risk_Register!$W$6="3-1",Risk_Register!$A$6&" ","")&IF(Risk_Register!$W$7="3-1",Risk_Register!$A$7&" ","")&IF(Risk_Register!$W$8="3-1",Risk_Register!$A$8&" ","")&IF(Risk_Register!$W$9="3-1",Risk_Register!$A$9&" ","")&IF(Risk_Register!$W$10="3-1",Risk_Register!$A$10&" ","")&IF(Risk_Register!$W$11="3-1",Risk_Register!$A$11&" ","")&IF(Risk_Register!$W$12="3-1",Risk_Register!$A$12&" ","")&IF(Risk_Register!$W$13="3-1",Risk_Register!$A$13&" ","")&IF(Risk_Register!$W$14="3-1",Risk_Register!$A$14&" ","")&IF(Risk_Register!$W$15="3-1",Risk_Register!$A$15&" ","")&IF(Risk_Register!$W$16="3-1",Risk_Register!$A$16&" ","")&IF(Risk_Register!$W$17="3-1",Risk_Register!$A$17&" ",""))) | I8: =IF(COUNTIFS(Risk_Register!$N$5:$N$17,3,Risk_Register!$O$5:$O$17,2)=0,"",COUNTIFS(Risk_Register!$N$5:$N$17,3,Risk_Register!$O$5:$O$17,2)&" · Medium"&CHAR(10)&TRIM(IF(Risk_Register!$W$5="3-2",Risk_Register!$A$5&" ","")&IF(Risk_Register!$W$6="3-2",Risk_Register!$A$6&" ","")&IF(Risk_Register!$W$7="3-2",Risk_Register!$A$7&" ","")&IF(Risk_Register!$W$8="3-2",Risk_Register!$A$8&" ","")&IF(Risk_Register!$W$9="3-2",Risk_Register!$A$9&" ","")&IF(Risk_Register!$W$10="3-2",Risk_Register!$A$10&" ","")&IF(Risk_Register!$W$11="3-2",Risk_Register!$A$11&" ","")&IF(Risk_Register!$W$12="3-2",Risk_Register!$A$12&" ","")&IF(Risk_Register!$W$13="3-2",Risk_Register!$A$13&" ","")&IF(Risk_Register!$W$14="3-2",Risk_Register!$A$14&" ","")&IF(Risk_Register!$W$15="3-2",Risk_Register!$A$15&" ","")&IF(Risk_Register!$W$16="3-2",Risk_Register!$A$16&" ","")&IF(Risk_Register!$W$17="3-2",Risk_Register!$A$17&" ",""))) | J8: =IF(COUNTIFS(Risk_Register!$N$5:$N$17,3,Risk_Register!$O$5:$O$17,3)=0,"",COUNTIFS(Risk_Register!$N$5:$N$17,3,Risk_Register!$O$5:$O$17,3)&" · Medium"&CHAR(10)&TRIM(IF(Risk_Register!$W$5="3-3",Risk_Register!$A$5&" ","")&IF(Risk_Register!$W$6="3-3",Risk_Register!$A$6&" ","")&IF(Risk_Register!$W$7="3-3",Risk_Register!$A$7&" ","")&IF(Risk_Register!$W$8="3-3",Risk_Register!$A$8&" ","")&IF(Risk_Register!$W$9="3-3",Risk_Register!$A$9&" ","")&IF(Risk_Register!$W$10="3-3",Risk_Register!$A$10&" ","")&IF(Risk_Register!$W$11="3-3",Risk_Register!$A$11&" ","")&IF(Risk_Register!$W$12="3-3",Risk_Register!$A$12&" ","")&IF(Risk_Register!$W$13="3-3",Risk_Register!$A$13&" ","")&IF(Risk_Register!$W$14="3-3",Risk_Register!$A$14&" ","")&IF(Risk_Register!$W$15="3-3",Risk_Register!$A$15&" ","")&IF(Risk_Register!$W$16="3-3",Risk_Register!$A$16&" ","")&IF(Risk_Register!$W$17="3-3",Risk_Register!$A$17&" ",""))) | K8: =IF(COUNTIFS(Risk_Register!$N$5:$N$17,3,Risk_Register!$O$5:$O$17,4)=0,"",COUNTIFS(Risk_Register!$N$5:$N$17,3,Risk_Register!$O$5:$O$17,4)&" · High"&CHAR(10)&TRIM(IF(Risk_Register!$W$5="3-4",Risk_Register!$A$5&" ","")&IF(Risk_Register!$W$6="3-4",Risk_Register!$A$6&" ","")&IF(Risk_Register!$W$7="3-4",Risk_Register!$A$7&" ","")&IF(Risk_Register!$W$8="3-4",Risk_Register!$A$8&" ","")&IF(Risk_Register!$W$9="3-4",Risk_Register!$A$9&" ","")&IF(Risk_Register!$W$10="3-4",Risk_Register!$A$10&" ","")&IF(Risk_Register!$W$11="3-4",Risk_Register!$A$11&" ","")&IF(Risk_Register!$W$12="3-4",Risk_Register!$A$12&" ","")&IF(Risk_Register!$W$13="3-4",Risk_Register!$A$13&" ","")&IF(Risk_Register!$W$14="3-4",Risk_Register!$A$14&" ","")&IF(Risk_Register!$W$15="3-4",Risk_Register!$A$15&" ","")&IF(Risk_Register!$W$16="3-4",Risk_Register!$A$16&" ","")&IF(Risk_Register!$W$17="3-4",Risk_Register!$A$17&" ",""))) | L8: =IF(COUNTIFS(Risk_Register!$N$5:$N$17,3,Risk_Register!$O$5:$O$17,5)=0,"",COUNTIFS(Risk_Register!$N$5:$N$17,3,Risk_Register!$O$5:$O$17,5)&" · High"&CHAR(10)&TRIM(IF(Risk_Register!$W$5="3-5",Risk_Register!$A$5&" ","")&IF(Risk_Register!$W$6="3-5",Risk_Register!$A$6&" ","")&IF(Risk_Register!$W$7="3-5",Risk_Register!$A$7&" ","")&IF(Risk_Register!$W$8="3-5",Risk_Register!$A$8&" ","")&IF(Risk_Register!$W$9="3-5",Risk_Register!$A$9&" ","")&IF(Risk_Register!$W$10="3-5",Risk_Register!$A$10&" ","")&IF(Risk_Register!$W$11="3-5",Risk_Register!$A$11&" ","")&IF(Risk_Register!$W$12="3-5",Risk_Register!$A$12&" ","")&IF(Risk_Register!$W$13="3-5",Risk_Register!$A$13&" ","")&IF(Risk_Register!$W$14="3-5",Risk_Register!$A$14&" ","")&IF(Risk_Register!$W$15="3-5",Risk_Register!$A$15&" ","")&IF(Risk_Register!$W$16="3-5",Risk_Register!$A$16&" ","")&IF(Risk_Register!$W$17="3-5",Risk_Register!$A$17&" ","")))
A9: 2 Unlikely | B9: =IF(COUNTIFS(Risk_Register!$F$5:$F$17,2,Risk_Register!$G$5:$G$17,1)=0,"",COUNTIFS(Risk_Register!$F$5:$F$17,2,Risk_Register!$G$5:$G$17,1)&" · Low"&CHAR(10)&TRIM(IF(Risk_Register!$V$5="2-1",Risk_Register!$A$5&" ","")&IF(Risk_Register!$V$6="2-1",Risk_Register!$A$6&" ","")&IF(Risk_Register!$V$7="2-1",Risk_Register!$A$7&" ","")&IF(Risk_Register!$V$8="2-1",Risk_Register!$A$8&" ","")&IF(Risk_Register!$V$9="2-1",Risk_Register!$A$9&" ","")&IF(Risk_Register!$V$10="2-1",Risk_Register!$A$10&" ","")&IF(Risk_Register!$V$11="2-1",Risk_Register!$A$11&" ","")&IF(Risk_Register!$V$12="2-1",Risk_Register!$A$12&" ","")&IF(Risk_Register!$V$13="2-1",Risk_Register!$A$13&" ","")&IF(Risk_Register!$V$14="2-1",Risk_Register!$A$14&" ","")&IF(Risk_Register!$V$15="2-1",Risk_Register!$A$15&" ","")&IF(Risk_Register!$V$16="2-1",Risk_Register!$A$16&" ","")&IF(Risk_Register!$V$17="2-1",Risk_Register!$A$17&" ",""))) | C9: =IF(COUNTIFS(Risk_Register!$F$5:$F$17,2,Risk_Register!$G$5:$G$17,2)=0,"",COUNTIFS(Risk_Register!$F$5:$F$17,2,Risk_Register!$G$5:$G$17,2)&" · Low"&CHAR(10)&TRIM(IF(Risk_Register!$V$5="2-2",Risk_Register!$A$5&" ","")&IF(Risk_Register!$V$6="2-2",Risk_Register!$A$6&" ","")&IF(Risk_Register!$V$7="2-2",Risk_Register!$A$7&" ","")&IF(Risk_Register!$V$8="2-2",Risk_Register!$A$8&" ","")&IF(Risk_Register!$V$9="2-2",Risk_Register!$A$9&" ","")&IF(Risk_Register!$V$10="2-2",Risk_Register!$A$10&" ","")&IF(Risk_Register!$V$11="2-2",Risk_Register!$A$11&" ","")&IF(Risk_Register!$V$12="2-2",Risk_Register!$A$12&" ","")&IF(Risk_Register!$V$13="2-2",Risk_Register!$A$13&" ","")&IF(Risk_Register!$V$14="2-2",Risk_Register!$A$14&" ","")&IF(Risk_Register!$V$15="2-2",Risk_Register!$A$15&" ","")&IF(Risk_Register!$V$16="2-2",Risk_Register!$A$16&" ","")&IF(Risk_Register!$V$17="2-2",Risk_Register!$A$17&" ",""))) | D9: =IF(COUNTIFS(Risk_Register!$F$5:$F$17,2,Risk_Register!$G$5:$G$17,3)=0,"",COUNTIFS(Risk_Register!$F$5:$F$17,2,Risk_Register!$G$5:$G$17,3)&" · Medium"&CHAR(10)&TRIM(IF(Risk_Register!$V$5="2-3",Risk_Register!$A$5&" ","")&IF(Risk_Register!$V$6="2-3",Risk_Register!$A$6&" ","")&IF(Risk_Register!$V$7="2-3",Risk_Register!$A$7&" ","")&IF(Risk_Register!$V$8="2-3",Risk_Register!$A$8&" ","")&IF(Risk_Register!$V$9="2-3",Risk_Register!$A$9&" ","")&IF(Risk_Register!$V$10="2-3",Risk_Register!$A$10&" ","")&IF(Risk_Register!$V$11="2-3",Risk_Register!$A$11&" ","")&IF(Risk_Register!$V$12="2-3",Risk_Register!$A$12&" ","")&IF(Risk_Register!$V$13="2-3",Risk_Register!$A$13&" ","")&IF(Risk_Register!$V$14="2-3",Risk_Register!$A$14&" ","")&IF(Risk_Register!$V$15="2-3",Risk_Register!$A$15&" ","")&IF(Risk_Register!$V$16="2-3",Risk_Register!$A$16&" ","")&IF(Risk_Register!$V$17="2-3",Risk_Register!$A$17&" ",""))) -> 1 · Medium R05 | E9: =IF(COUNTIFS(Risk_Register!$F$5:$F$17,2,Risk_Register!$G$5:$G$17,4)=0,"",COUNTIFS(Risk_Register!$F$5:$F$17,2,Risk_Register!$G$5:$G$17,4)&" · Medium"&CHAR(10)&TRIM(IF(Risk_Register!$V$5="2-4",Risk_Register!$A$5&" ","")&IF(Risk_Register!$V$6="2-4",Risk_Register!$A$6&" ","")&IF(Risk_Register!$V$7="2-4",Risk_Register!$A$7&" ","")&IF(Risk_Register!$V$8="2-4",Risk_Register!$A$8&" ","")&IF(Risk_Register!$V$9="2-4",Risk_Register!$A$9&" ","")&IF(Risk_Register!$V$10="2-4",Risk_Register!$A$10&" ","")&IF(Risk_Register!$V$11="2-4",Risk_Register!$A$11&" ","")&IF(Risk_Register!$V$12="2-4",Risk_Register!$A$12&" ","")&IF(Risk_Register!$V$13="2-4",Risk_Register!$A$13&" ","")&IF(Risk_Register!$V$14="2-4",Risk_Register!$A$14&" ","")&IF(Risk_Register!$V$15="2-4",Risk_Register!$A$15&" ","")&IF(Risk_Register!$V$16="2-4",Risk_Register!$A$16&" ","")&IF(Risk_Register!$V$17="2-4",Risk_Register!$A$17&" ",""))) | F9: =IF(COUNTIFS(Risk_Register!$F$5:$F$17,2,Risk_Register!$G$5:$G$17,5)=0,"",COUNTIFS(Risk_Register!$F$5:$F$17,2,Risk_Register!$G$5:$G$17,5)&" · High"&CHAR(10)&TRIM(IF(Risk_Register!$V$5="2-5",Risk_Register!$A$5&" ","")&IF(Risk_Register!$V$6="2-5",Risk_Register!$A$6&" ","")&IF(Risk_Register!$V$7="2-5",Risk_Register!$A$7&" ","")&IF(Risk_Register!$V$8="2-5",Risk_Register!$A$8&" ","")&IF(Risk_Register!$V$9="2-5",Risk_Register!$A$9&" ","")&IF(Risk_Register!$V$10="2-5",Risk_Register!$A$10&" ","")&IF(Risk_Register!$V$11="2-5",Risk_Register!$A$11&" ","")&IF(Risk_Register!$V$12="2-5",Risk_Register!$A$12&" ","")&IF(Risk_Register!$V$13="2-5",Risk_Register!$A$13&" ","")&IF(Risk_Register!$V$14="2-5",Risk_Register!$A$14&" ","")&IF(Risk_Register!$V$15="2-5",Risk_Register!$A$15&" ","")&IF(Risk_Register!$V$16="2-5",Risk_Register!$A$16&" ","")&IF(Risk_Register!$V$17="2-5",Risk_Register!$A$17&" ",""))) -> 1 · High R03 | G9: 2 Unlikely | H9: =IF(COUNTIFS(Risk_Register!$N$5:$N$17,2,Risk_Register!$O$5:$O$17,1)=0,"",COUNTIFS(Risk_Register!$N$5:$N$17,2,Risk_Register!$O$5:$O$17,1)&" · Low"&CHAR(10)&TRIM(IF(Risk_Register!$W$5="2-1",Risk_Register!$A$5&" ","")&IF(Risk_Register!$W$6="2-1",Risk_Register!$A$6&" ","")&IF(Risk_Register!$W$7="2-1",Risk_Register!$A$7&" ","")&IF(Risk_Register!$W$8="2-1",Risk_Register!$A$8&" ","")&IF(Risk_Register!$W$9="2-1",Risk_Register!$A$9&" ","")&IF(Risk_Register!$W$10="2-1",Risk_Register!$A$10&" ","")&IF(Risk_Register!$W$11="2-1",Risk_Register!$A$11&" ","")&IF(Risk_Register!$W$12="2-1",Risk_Register!$A$12&" ","")&IF(Risk_Register!$W$13="2-1",Risk_Register!$A$13&" ","")&IF(Risk_Register!$W$14="2-1",Risk_Register!$A$14&" ","")&IF(Risk_Register!$W$15="2-1",Risk_Register!$A$15&" ","")&IF(Risk_Register!$W$16="2-1",Risk_Register!$A$16&" ","")&IF(Risk_Register!$W$17="2-1",Risk_Register!$A$17&" ",""))) | I9: =IF(COUNTIFS(Risk_Register!$N$5:$N$17,2,Risk_Register!$O$5:$O$17,2)=0,"",COUNTIFS(Risk_Register!$N$5:$N$17,2,Risk_Register!$O$5:$O$17,2)&" · Low"&CHAR(10)&TRIM(IF(Risk_Register!$W$5="2-2",Risk_Register!$A$5&" ","")&IF(Risk_Register!$W$6="2-2",Risk_Register!$A$6&" ","")&IF(Risk_Register!$W$7="2-2",Risk_Register!$A$7&" ","")&IF(Risk_Register!$W$8="2-2",Risk_Register!$A$8&" ","")&IF(Risk_Register!$W$9="2-2",Risk_Register!$A$9&" ","")&IF(Risk_Register!$W$10="2-2",Risk_Register!$A$10&" ","")&IF(Risk_Register!$W$11="2-2",Risk_Register!$A$11&" ","")&IF(Risk_Register!$W$12="2-2",Risk_Register!$A$12&" ","")&IF(Risk_Register!$W$13="2-2",Risk_Register!$A$13&" ","")&IF(Risk_Register!$W$14="2-2",Risk_Register!$A$14&" ","")&IF(Risk_Register!$W$15="2-2",Risk_Register!$A$15&" ","")&IF(Risk_Register!$W$16="2-2",Risk_Register!$A$16&" ","")&IF(Risk_Register!$W$17="2-2",Risk_Register!$A$17&" ",""))) -> 2 · Low R05 R09 | J9: =IF(COUNTIFS(Risk_Register!$N$5:$N$17,2,Risk_Register!$O$5:$O$17,3)=0,"",COUNTIFS(Risk_Register!$N$5:$N$17,2,Risk_Register!$O$5:$O$17,3)&" · Medium"&CHAR(10)&TRIM(IF(Risk_Register!$W$5="2-3",Risk_Register!$A$5&" ","")&IF(Risk_Register!$W$6="2-3",Risk_Register!$A$6&" ","")&IF(Risk_Register!$W$7="2-3",Risk_Register!$A$7&" ","")&IF(Risk_Register!$W$8="2-3",Risk_Register!$A$8&" ","")&IF(Risk_Register!$W$9="2-3",Risk_Register!$A$9&" ","")&IF(Risk_Register!$W$10="2-3",Risk_Register!$A$10&" ","")&IF(Risk_Register!$W$11="2-3",Risk_Register!$A$11&" ","")&IF(Risk_Register!$W$12="2-3",Risk_Register!$A$12&" ","")&IF(Risk_Register!$W$13="2-3",Risk_Register!$A$13&" ","")&IF(Risk_Register!$W$14="2-3",Risk_Register!$A$14&" ","")&IF(Risk_Register!$W$15="2-3",Risk_Register!$A$15&" ","")&IF(Risk_Register!$W$16="2-3",Risk_Register!$A$16&" ","")&IF(Risk_Register!$W$17="2-3",Risk_Register!$A$17&" ",""))) -> 4 · Medium R01 R02 R06 R11 | K9: =IF(COUNTIFS(Risk_Register!$N$5:$N$17,2,Risk_Register!$O$5:$O$17,4)=0,"",COUNTIFS(Risk_Register!$N$5:$N$17,2,Risk_Register!$O$5:$O$17,4)&" · Medium"&CHAR(10)&TRIM(IF(Risk_Register!$W$5="2-4",Risk_Register!$A$5&" ","")&IF(Risk_Register!$W$6="2-4",Risk_Register!$A$6&" ","")&IF(Risk_Register!$W$7="2-4",Risk_Register!$A$7&" ","")&IF(Risk_Register!$W$8="2-4",Risk_Register!$A$8&" ","")&IF(Risk_Register!$W$9="2-4",Risk_Register!$A$9&" ","")&IF(Risk_Register!$W$10="2-4",Risk_Register!$A$10&" ","")&IF(Risk_Register!$W$11="2-4",Risk_Register!$A$11&" ","")&IF(Risk_Register!$W$12="2-4",Risk_Register!$A$12&" ","")&IF(Risk_Register!$W$13="2-4",Risk_Register!$A$13&" ","")&IF(Risk_Register!$W$14="2-4",Risk_Register!$A$14&" ","")&IF(Risk_Register!$W$15="2-4",Risk_Register!$A$15&" ","")&IF(Risk_Register!$W$16="2-4",Risk_Register!$A$16&" ","")&IF(Risk_Register!$W$17="2-4",Risk_Register!$A$17&" ",""))) -> 1 · Medium R07 | L9: =IF(COUNTIFS(Risk_Register!$N$5:$N$17,2,Risk_Register!$O$5:$O$17,5)=0,"",COUNTIFS(Risk_Register!$N$5:$N$17,2,Risk_Register!$O$5:$O$17,5)&" · High"&CHAR(10)&TRIM(IF(Risk_Register!$W$5="2-5",Risk_Register!$A$5&" ","")&IF(Risk_Register!$W$6="2-5",Risk_Register!$A$6&" ","")&IF(Risk_Register!$W$7="2-5",Risk_Register!$A$7&" ","")&IF(Risk_Register!$W$8="2-5",Risk_Register!$A$8&" ","")&IF(Risk_Register!$W$9="2-5",Risk_Register!$A$9&" ","")&IF(Risk_Register!$W$10="2-5",Risk_Register!$A$10&" ","")&IF(Risk_Register!$W$11="2-5",Risk_Register!$A$11&" ","")&IF(Risk_Register!$W$12="2-5",Risk_Register!$A$12&" ","")&IF(Risk_Register!$W$13="2-5",Risk_Register!$A$13&" ","")&IF(Risk_Register!$W$14="2-5",Risk_Register!$A$14&" ","")&IF(Risk_Register!$W$15="2-5",Risk_Register!$A$15&" ","")&IF(Risk_Register!$W$16="2-5",Risk_Register!$A$16&" ","")&IF(Risk_Register!$W$17="2-5",Risk_Register!$A$17&" ","")))
A10: 1 Rare | B10: =IF(COUNTIFS(Risk_Register!$F$5:$F$17,1,Risk_Register!$G$5:$G$17,1)=0,"",COUNTIFS(Risk_Register!$F$5:$F$17,1,Risk_Register!$G$5:$G$17,1)&" · Low"&CHAR(10)&TRIM(IF(Risk_Register!$V$5="1-1",Risk_Register!$A$5&" ","")&IF(Risk_Register!$V$6="1-1",Risk_Register!$A$6&" ","")&IF(Risk_Register!$V$7="1-1",Risk_Register!$A$7&" ","")&IF(Risk_Register!$V$8="1-1",Risk_Register!$A$8&" ","")&IF(Risk_Register!$V$9="1-1",Risk_Register!$A$9&" ","")&IF(Risk_Register!$V$10="1-1",Risk_Register!$A$10&" ","")&IF(Risk_Register!$V$11="1-1",Risk_Register!$A$11&" ","")&IF(Risk_Register!$V$12="1-1",Risk_Register!$A$12&" ","")&IF(Risk_Register!$V$13="1-1",Risk_Register!$A$13&" ","")&IF(Risk_Register!$V$14="1-1",Risk_Register!$A$14&" ","")&IF(Risk_Register!$V$15="1-1",Risk_Register!$A$15&" ","")&IF(Risk_Register!$V$16="1-1",Risk_Register!$A$16&" ","")&IF(Risk_Register!$V$17="1-1",Risk_Register!$A$17&" ",""))) | C10: =IF(COUNTIFS(Risk_Register!$F$5:$F$17,1,Risk_Register!$G$5:$G$17,2)=0,"",COUNTIFS(Risk_Register!$F$5:$F$17,1,Risk_Register!$G$5:$G$17,2)&" · Low"&CHAR(10)&TRIM(IF(Risk_Register!$V$5="1-2",Risk_Register!$A$5&" ","")&IF(Risk_Register!$V$6="1-2",Risk_Register!$A$6&" ","")&IF(Risk_Register!$V$7="1-2",Risk_Register!$A$7&" ","")&IF(Risk_Register!$V$8="1-2",Risk_Register!$A$8&" ","")&IF(Risk_Register!$V$9="1-2",Risk_Register!$A$9&" ","")&IF(Risk_Register!$V$10="1-2",Risk_Register!$A$10&" ","")&IF(Risk_Register!$V$11="1-2",Risk_Register!$A$11&" ","")&IF(Risk_Register!$V$12="1-2",Risk_Register!$A$12&" ","")&IF(Risk_Register!$V$13="1-2",Risk_Register!$A$13&" ","")&IF(Risk_Register!$V$14="1-2",Risk_Register!$A$14&" ","")&IF(Risk_Register!$V$15="1-2",Risk_Register!$A$15&" ","")&IF(Risk_Register!$V$16="1-2",Risk_Register!$A$16&" ","")&IF(Risk_Register!$V$17="1-2",Risk_Register!$A$17&" ",""))) | D10: =IF(COUNTIFS(Risk_Register!$F$5:$F$17,1,Risk_Register!$G$5:$G$17,3)=0,"",COUNTIFS(Risk_Register!$F$5:$F$17,1,Risk_Register!$G$5:$G$17,3)&" · Low"&CHAR(10)&TRIM(IF(Risk_Register!$V$5="1-3",Risk_Register!$A$5&" ","")&IF(Risk_Register!$V$6="1-3",Risk_Register!$A$6&" ","")&IF(Risk_Register!$V$7="1-3",Risk_Register!$A$7&" ","")&IF(Risk_Register!$V$8="1-3",Risk_Register!$A$8&" ","")&IF(Risk_Register!$V$9="1-3",Risk_Register!$A$9&" ","")&IF(Risk_Register!$V$10="1-3",Risk_Register!$A$10&" ","")&IF(Risk_Register!$V$11="1-3",Risk_Register!$A$11&" ","")&IF(Risk_Register!$V$12="1-3",Risk_Register!$A$12&" ","")&IF(Risk_Register!$V$13="1-3",Risk_Register!$A$13&" ","")&IF(Risk_Register!$V$14="1-3",Risk_Register!$A$14&" ","")&IF(Risk_Register!$V$15="1-3",Risk_Register!$A$15&" ","")&IF(Risk_Register!$V$16="1-3",Risk_Register!$A$16&" ","")&IF(Risk_Register!$V$17="1-3",Risk_Register!$A$17&" ",""))) | E10: =IF(COUNTIFS(Risk_Register!$F$5:$F$17,1,Risk_Register!$G$5:$G$17,4)=0,"",COUNTIFS(Risk_Register!$F$5:$F$17,1,Risk_Register!$G$5:$G$17,4)&" · Low"&CHAR(10)&TRIM(IF(Risk_Register!$V$5="1-4",Risk_Register!$A$5&" ","")&IF(Risk_Register!$V$6="1-4",Risk_Register!$A$6&" ","")&IF(Risk_Register!$V$7="1-4",Risk_Register!$A$7&" ","")&IF(Risk_Register!$V$8="1-4",Risk_Register!$A$8&" ","")&IF(Risk_Register!$V$9="1-4",Risk_Register!$A$9&" ","")&IF(Risk_Register!$V$10="1-4",Risk_Register!$A$10&" ","")&IF(Risk_Register!$V$11="1-4",Risk_Register!$A$11&" ","")&IF(Risk_Register!$V$12="1-4",Risk_Register!$A$12&" ","")&IF(Risk_Register!$V$13="1-4",Risk_Register!$A$13&" ","")&IF(Risk_Register!$V$14="1-4",Risk_Register!$A$14&" ","")&IF(Risk_Register!$V$15="1-4",Risk_Register!$A$15&" ","")&IF(Risk_Register!$V$16="1-4",Risk_Register!$A$16&" ","")&IF(Risk_Register!$V$17="1-4",Risk_Register!$A$17&" ",""))) | F10: =IF(COUNTIFS(Risk_Register!$F$5:$F$17,1,Risk_Register!$G$5:$G$17,5)=0,"",COUNTIFS(Risk_Register!$F$5:$F$17,1,Risk_Register!$G$5:$G$17,5)&" · Medium"&CHAR(10)&TRIM(IF(Risk_Register!$V$5="1-5",Risk_Register!$A$5&" ","")&IF(Risk_Register!$V$6="1-5",Risk_Register!$A$6&" ","")&IF(Risk_Register!$V$7="1-5",Risk_Register!$A$7&" ","")&IF(Risk_Register!$V$8="1-5",Risk_Register!$A$8&" ","")&IF(Risk_Register!$V$9="1-5",Risk_Register!$A$9&" ","")&IF(Risk_Register!$V$10="1-5",Risk_Register!$A$10&" ","")&IF(Risk_Register!$V$11="1-5",Risk_Register!$A$11&" ","")&IF(Risk_Register!$V$12="1-5",Risk_Register!$A$12&" ","")&IF(Risk_Register!$V$13="1-5",Risk_Register!$A$13&" ","")&IF(Risk_Register!$V$14="1-5",Risk_Register!$A$14&" ","")&IF(Risk_Register!$V$15="1-5",Risk_Register!$A$15&" ","")&IF(Risk_Register!$V$16="1-5",Risk_Register!$A$16&" ","")&IF(Risk_Register!$V$17="1-5",Risk_Register!$A$17&" ",""))) | G10: 1 Rare | H10: =IF(COUNTIFS(Risk_Register!$N$5:$N$17,1,Risk_Register!$O$5:$O$17,1)=0,"",COUNTIFS(Risk_Register!$N$5:$N$17,1,Risk_Register!$O$5:$O$17,1)&" · Low"&CHAR(10)&TRIM(IF(Risk_Register!$W$5="1-1",Risk_Register!$A$5&" ","")&IF(Risk_Register!$W$6="1-1",Risk_Register!$A$6&" ","")&IF(Risk_Register!$W$7="1-1",Risk_Register!$A$7&" ","")&IF(Risk_Register!$W$8="1-1",Risk_Register!$A$8&" ","")&IF(Risk_Register!$W$9="1-1",Risk_Register!$A$9&" ","")&IF(Risk_Register!$W$10="1-1",Risk_Register!$A$10&" ","")&IF(Risk_Register!$W$11="1-1",Risk_Register!$A$11&" ","")&IF(Risk_Register!$W$12="1-1",Risk_Register!$A$12&" ","")&IF(Risk_Register!$W$13="1-1",Risk_Register!$A$13&" ","")&IF(Risk_Register!$W$14="1-1",Risk_Register!$A$14&" ","")&IF(Risk_Register!$W$15="1-1",Risk_Register!$A$15&" ","")&IF(Risk_Register!$W$16="1-1",Risk_Register!$A$16&" ","")&IF(Risk_Register!$W$17="1-1",Risk_Register!$A$17&" ",""))) | I10: =IF(COUNTIFS(Risk_Register!$N$5:$N$17,1,Risk_Register!$O$5:$O$17,2)=0,"",COUNTIFS(Risk_Register!$N$5:$N$17,1,Risk_Register!$O$5:$O$17,2)&" · Low"&CHAR(10)&TRIM(IF(Risk_Register!$W$5="1-2",Risk_Register!$A$5&" ","")&IF(Risk_Register!$W$6="1-2",Risk_Register!$A$6&" ","")&IF(Risk_Register!$W$7="1-2",Risk_Register!$A$7&" ","")&IF(Risk_Register!$W$8="1-2",Risk_Register!$A$8&" ","")&IF(Risk_Register!$W$9="1-2",Risk_Register!$A$9&" ","")&IF(Risk_Register!$W$10="1-2",Risk_Register!$A$10&" ","")&IF(Risk_Register!$W$11="1-2",Risk_Register!$A$11&" ","")&IF(Risk_Register!$W$12="1-2",Risk_Register!$A$12&" ","")&IF(Risk_Register!$W$13="1-2",Risk_Register!$A$13&" ","")&IF(Risk_Register!$W$14="1-2",Risk_Register!$A$14&" ","")&IF(Risk_Register!$W$15="1-2",Risk_Register!$A$15&" ","")&IF(Risk_Register!$W$16="1-2",Risk_Register!$A$16&" ","")&IF(Risk_Register!$W$17="1-2",Risk_Register!$A$17&" ",""))) | J10: =IF(COUNTIFS(Risk_Register!$N$5:$N$17,1,Risk_Register!$O$5:$O$17,3)=0,"",COUNTIFS(Risk_Register!$N$5:$N$17,1,Risk_Register!$O$5:$O$17,3)&" · Low"&CHAR(10)&TRIM(IF(Risk_Register!$W$5="1-3",Risk_Register!$A$5&" ","")&IF(Risk_Register!$W$6="1-3",Risk_Register!$A$6&" ","")&IF(Risk_Register!$W$7="1-3",Risk_Register!$A$7&" ","")&IF(Risk_Register!$W$8="1-3",Risk_Register!$A$8&" ","")&IF(Risk_Register!$W$9="1-3",Risk_Register!$A$9&" ","")&IF(Risk_Register!$W$10="1-3",Risk_Register!$A$10&" ","")&IF(Risk_Register!$W$11="1-3",Risk_Register!$A$11&" ","")&IF(Risk_Register!$W$12="1-3",Risk_Register!$A$12&" ","")&IF(Risk_Register!$W$13="1-3",Risk_Register!$A$13&" ","")&IF(Risk_Register!$W$14="1-3",Risk_Register!$A$14&" ","")&IF(Risk_Register!$W$15="1-3",Risk_Register!$A$15&" ","")&IF(Risk_Register!$W$16="1-3",Risk_Register!$A$16&" ","")&IF(Risk_Register!$W$17="1-3",Risk_Register!$A$17&" ",""))) -> 2 · Low R08 R10 | K10: =IF(COUNTIFS(Risk_Register!$N$5:$N$17,1,Risk_Register!$O$5:$O$17,4)=0,"",COUNTIFS(Risk_Register!$N$5:$N$17,1,Risk_Register!$O$5:$O$17,4)&" · Low"&CHAR(10)&TRIM(IF(Risk_Register!$W$5="1-4",Risk_Register!$A$5&" ","")&IF(Risk_Register!$W$6="1-4",Risk_Register!$A$6&" ","")&IF(Risk_Register!$W$7="1-4",Risk_Register!$A$7&" ","")&IF(Risk_Register!$W$8="1-4",Risk_Register!$A$8&" ","")&IF(Risk_Register!$W$9="1-4",Risk_Register!$A$9&" ","")&IF(Risk_Register!$W$10="1-4",Risk_Register!$A$10&" ","")&IF(Risk_Register!$W$11="1-4",Risk_Register!$A$11&" ","")&IF(Risk_Register!$W$12="1-4",Risk_Register!$A$12&" ","")&IF(Risk_Register!$W$13="1-4",Risk_Register!$A$13&" ","")&IF(Risk_Register!$W$14="1-4",Risk_Register!$A$14&" ","")&IF(Risk_Register!$W$15="1-4",Risk_Register!$A$15&" ","")&IF(Risk_Register!$W$16="1-4",Risk_Register!$A$16&" ","")&IF(Risk_Register!$W$17="1-4",Risk_Register!$A$17&" ",""))) -> 1 · Low R04 | L10: =IF(COUNTIFS(Risk_Register!$N$5:$N$17,1,Risk_Register!$O$5:$O$17,5)=0,"",COUNTIFS(Risk_Register!$N$5:$N$17,1,Risk_Register!$O$5:$O$17,5)&" · Medium"&CHAR(10)&TRIM(IF(Risk_Register!$W$5="1-5",Risk_Register!$A$5&" ","")&IF(Risk_Register!$W$6="1-5",Risk_Register!$A$6&" ","")&IF(Risk_Register!$W$7="1-5",Risk_Register!$A$7&" ","")&IF(Risk_Register!$W$8="1-5",Risk_Register!$A$8&" ","")&IF(Risk_Register!$W$9="1-5",Risk_Register!$A$9&" ","")&IF(Risk_Register!$W$10="1-5",Risk_Register!$A$10&" ","")&IF(Risk_Register!$W$11="1-5",Risk_Register!$A$11&" ","")&IF(Risk_Register!$W$12="1-5",Risk_Register!$A$12&" ","")&IF(Risk_Register!$W$13="1-5",Risk_Register!$A$13&" ","")&IF(Risk_Register!$W$14="1-5",Risk_Register!$A$14&" ","")&IF(Risk_Register!$W$15="1-5",Risk_Register!$A$15&" ","")&IF(Risk_Register!$W$16="1-5",Risk_Register!$A$16&" ","")&IF(Risk_Register!$W$17="1-5",Risk_Register!$A$17&" ",""))) -> 1 · Medium R03
A12: Risks plotted | B12: =COUNT(Risk_Register!$F$5:$F$17) -> 13 | G12: Risks plotted | H12: =COUNT(Risk_Register!$N$5:$N$17) -> 13
A14: Check: heat-map count equals register count | B14: =IF(B12=COUNTA(Risk_Register!A5:A17),"OK","MISMATCH") -> OK
A15: What it shows: seven threats start as High (R01 at 4×4 is the worst one). After our responses none of them is above Medium. R03 stays Medium (1×5) because a data breach would still be really bad. R12 is an opportunity, so we want it to happen: its residual score (5×3) being high is a good thing.

Sheet Cost_Baseline
A1: Cost baseline, reserves and budget (AUD)
A2: UniConnect — Student Portal Consolidation | Status date 25/09/2026 | Source: data/project.yaml
A4: WBS | B4: Level-1 deliverable | C4: Labour hours | D4: Labour cost | E4: Fixed / material | F4: Subtotal | G4: % of BAC | I4: Month | J4: Planned value (month) | K4: Cumulative PV | L4: % of BAC
A5: 1 | B5: Project Management | C5: =SUMPRODUCT((Schedule_WBS!$B$5:$B$41=A5)*1,SUMIF(Assignments!$A$5:$A$84,Schedule_WBS!$A$5:$A$41,Assignments!$E$5:$E$84)) -> 1120 | D5: =SUMIF(Schedule_WBS!$B$5:$B$41,A5,Schedule_WBS!$L$5:$L$41) -> 125520 | E5: =SUMIF(Schedule_WBS!$B$5:$B$41,A5,Schedule_WBS!$M$5:$M$41) -> 0 | F5: =D5+E5 -> 125520 | G5: =F5/$F$12 -> 0.13943878 | I5: Jul 2026 | J5: 42500 | K5: =J5 -> 42500 | L5: =K5/$F$12 -> 0.04721278
A6: 2 | B6: Requirements & Design | C6: =SUMPRODUCT((Schedule_WBS!$B$5:$B$41=A6)*1,SUMIF(Assignments!$A$5:$A$84,Schedule_WBS!$A$5:$A$41,Assignments!$E$5:$E$84)) -> 700 | D6: =SUMIF(Schedule_WBS!$B$5:$B$41,A6,Schedule_WBS!$L$5:$L$41) -> 76900 | E6: =SUMIF(Schedule_WBS!$B$5:$B$41,A6,Schedule_WBS!$M$5:$M$41) -> 0 | F6: =D6+E6 -> 76900 | G6: =F6/$F$12 -> 0.085427359 | I6: Aug 2026 | J6: 72960 | K6: =K5+J6 -> 115460 | L6: =K6/$F$12 -> 0.12826324
A7: 3 | B7: Portal Build (Agile) | C7: =SUMPRODUCT((Schedule_WBS!$B$5:$B$41=A7)*1,SUMIF(Assignments!$A$5:$A$84,Schedule_WBS!$A$5:$A$41,Assignments!$E$5:$E$84)) -> 1500 | D7: =SUMIF(Schedule_WBS!$B$5:$B$41,A7,Schedule_WBS!$L$5:$L$41) -> 150800 | E7: =SUMIF(Schedule_WBS!$B$5:$B$41,A7,Schedule_WBS!$M$5:$M$41) -> 0 | F7: =D7+E7 -> 150800 | G7: =F7/$F$12 -> 0.16752205 | I7: Sep 2026 | J7: 143480 | K7: =K6+J7 -> 258940 | L7: =K7/$F$12 -> 0.28765358
A8: 4 | B8: Data Migration | C8: =SUMPRODUCT((Schedule_WBS!$B$5:$B$41=A8)*1,SUMIF(Assignments!$A$5:$A$84,Schedule_WBS!$A$5:$A$41,Assignments!$E$5:$E$84)) -> 740 | D8: =SUMIF(Schedule_WBS!$B$5:$B$41,A8,Schedule_WBS!$L$5:$L$41) -> 76400 | E8: =SUMIF(Schedule_WBS!$B$5:$B$41,A8,Schedule_WBS!$M$5:$M$41) -> 0 | F8: =D8+E8 -> 76400 | G8: =F8/$F$12 -> 0.084871915 | I8: Oct 2026 | J8: 136190 | K8: =K7+J8 -> 395130 | L8: =K8/$F$12 -> 0.43894554
A9: 5 | B9: Testing & Quality | C9: =SUMPRODUCT((Schedule_WBS!$B$5:$B$41=A9)*1,SUMIF(Assignments!$A$5:$A$84,Schedule_WBS!$A$5:$A$41,Assignments!$E$5:$E$84)) -> 1140 | D9: =SUMIF(Schedule_WBS!$B$5:$B$41,A9,Schedule_WBS!$L$5:$L$41) -> 115160 | E9: =SUMIF(Schedule_WBS!$B$5:$B$41,A9,Schedule_WBS!$M$5:$M$41) -> 25000 | F9: =D9+E9 -> 140160 | G9: =F9/$F$12 -> 0.15570219 | I9: Nov 2026 | J9: 113120 | K9: =K8+J9 -> 508250 | L9: =K9/$F$12 -> 0.5646093
A10: 6 | B10: Deployment & Transition | C10: =SUMPRODUCT((Schedule_WBS!$B$5:$B$41=A10)*1,SUMIF(Assignments!$A$5:$A$84,Schedule_WBS!$A$5:$A$41,Assignments!$E$5:$E$84)) -> 1040 | D10: =SUMIF(Schedule_WBS!$B$5:$B$41,A10,Schedule_WBS!$L$5:$L$41) -> 106400 | E10: =SUMIF(Schedule_WBS!$B$5:$B$41,A10,Schedule_WBS!$M$5:$M$41) -> 224000 | F10: =D10+E10 -> 330400 | G10: =F10/$F$12 -> 0.3670377 | I10: Dec 2026 | J10: 56610 | K10: =K9+J10 -> 564860 | L10: =K10/$F$12 -> 0.62749672
I11: Jan 2027 | J11: 275250 | K11: =K10+J11 -> 840110 | L11: =K11/$F$12 -> 0.9332689
B12: Cost baseline (BAC) | C12: =SUM(C5:C10) -> 6240 | D12: =SUM(D5:D10) -> 651180 | E12: =SUM(E5:E10) -> 249000 | F12: =SUM(F5:F10) -> 900180 | G12: =F12/F12 -> 1 | I12: Feb 2027 | J12: 49370 | K12: =K11+J12 -> 889480 | L12: =K12/$F$12 -> 0.98811349
B13: Contingency reserve (Σ threat EMV, Risk_Register) | F13: =Contingency -> 90750 | G13: =F13/F12 -> 0.10081317 | I13: Mar 2027 | J13: 10700 | K13: =K12+J13 -> 900180 | L13: =K13/$F$12 -> 1
B14: Performance measurement baseline = BAC + contingency | F14: =F12+F13 -> 990930 | I14: Monthly PV is time-phased from the ProjectLibre baseline (flat work contour).
B15: Management reserve (5% of BAC, sponsor-held) | F15: =F12*5/100 -> 45009 | G15: =F15/F12 -> 0.05
B16: Total project budget | F16: =F14+F15 -> 1035939
B17: Check: BAC equals Schedule_WBS total | F17: =IF(ABS(F12-BAC)<1,"OK","MISMATCH") -> OK

Sheet EVM_Status
A1: Earned value status (to 25 Sep 2026)
A2: Weekly cumulative PV/EV/AC from the ProjectLibre baseline and progress; summary uses the Schedule_WBS task totals
K3: Status-date summary
A4: Week | B4: Week ending | C4: PV (cum) | D4: EV (cum) | E4: AC (cum) | F4: SV | G4: CV | H4: SPI | I4: CPI | K4: Budget at completion (BAC) | L4: =BAC -> 900180 | N4: Cost baseline (Schedule_WBS)
A5: 1 | B5: 46213 | C5: 6700 | D5: 6700 | E5: 6700 | F5: =D5-C5 -> 0 | G5: =D5-E5 -> 0 | H5: =IF(C5=0,"",D5/C5) -> 1 | I5: =IF(E5=0,"",D5/E5) -> 1 | K5: Planned value (PV / BCWS) | L5: =PV_total -> 242800 | N5: ProjectLibre BCWS at status date
A6: 2 | B6: 46220 | C6: 13400 | D6: 13400 | E6: 13400 | F6: =D6-C6 -> 0 | G6: =D6-E6 -> 0 | H6: =IF(C6=0,"",D6/C6) -> 1 | I6: =IF(E6=0,"",D6/E6) -> 1 | K6: Earned value (EV / BCWP) | L6: =EV_total -> 221830 | N6: % complete × baseline cost
A7: 3 | B7: 46227 | C7: 28900 | D7: 28900 | E7: 28900 | F7: =D7-C7 -> 0 | G7: =D7-E7 -> 0 | H7: =IF(C7=0,"",D7/C7) -> 1 | I7: =IF(E7=0,"",D7/E7) -> 1 | K7: Actual cost (AC / ACWP) | L7: =AC_total -> 231730 | N7: ProjectLibre actual cost
A8: 4 | B8: 46234 | C8: 42500 | D8: 42500 | E8: 42500 | F8: =D8-C8 -> 0 | G8: =D8-E8 -> 0 | H8: =IF(C8=0,"",D8/C8) -> 1 | I8: =IF(E8=0,"",D8/E8) -> 1 | K8: Schedule variance SV = EV − PV | L8: =L6-L5 -> -20970 | N8: Negative = behind schedule
A9: 5 | B9: 46241 | C9: 53650 | D9: 53650 | E9: 53650 | F9: =D9-C9 -> 0 | G9: =D9-E9 -> 0 | H9: =IF(C9=0,"",D9/C9) -> 1 | I9: =IF(E9=0,"",D9/E9) -> 1 | K9: Cost variance CV = EV − AC | L9: =L6-L7 -> -9900 | N9: Negative = over budget
A10: 6 | B10: 46248 | C10: 64800 | D10: 64800 | E10: 64800 | F10: =D10-C10 -> 0 | G10: =D10-E10 -> 0 | H10: =IF(C10=0,"",D10/C10) -> 1 | I10: =IF(E10=0,"",D10/E10) -> 1 | K10: SPI = EV / PV | L10: =L6/L5 -> 0.91363262 | M10: =IF(L10="","",IF(L10>=0.95,"Green",IF(L10>=0.9,"Amber","Red"))) -> Amber | N10: < 1 behind schedule
A11: 7 | B11: 46255 | C11: 83350 | D11: 83350 | E11: 85210 | F11: =D11-C11 -> 0 | G11: =D11-E11 -> -1860 | H11: =IF(C11=0,"",D11/C11) -> 1 | I11: =IF(E11=0,"",D11/E11) -> 0.97817158 | K11: CPI = EV / AC | L11: =L6/L7 -> 0.95727787 | M11: =IF(L11="","",IF(L11>=0.95,"Green",IF(L11>=0.9,"Amber","Red"))) -> Green | N11: < 1 over budget
A12: 8 | B12: 46262 | C12: 107000 | D12: 107000 | E12: 110720 | F12: =D12-C12 -> 0 | G12: =D12-E12 -> -3720 | H12: =IF(C12=0,"",D12/C12) -> 1 | I12: =IF(E12=0,"",D12/E12) -> 0.96640173 | K12: EAC (typical) = BAC / CPI | L12: =L4/L11 -> 940353.93 | N12: Current cost efficiency continues
A13: 9 | B13: 46269 | C13: 149300 | D13: 147200 | E13: 152180 | F13: =D13-C13 -> -2100 | G13: =D13-E13 -> -4980 | H13: =IF(C13=0,"",D13/C13) -> 0.98593436 | I13: =IF(E13=0,"",D13/E13) -> 0.96727559 | K13: EAC (atypical) = AC + (BAC − EV) | L13: =L7+(L4-L6) -> 910080 | N13: Variance treated as one-off
A14: 10 | B14: 46276 | C14: 180600 | D14: 176400 | E14: 182640 | F14: =D14-C14 -> -4200 | G14: =D14-E14 -> -6240 | H14: =IF(C14=0,"",D14/C14) -> 0.97674419 | I14: =IF(E14=0,"",D14/E14) -> 0.96583443 | K14: EAC (CPI × SPI) = AC + (BAC − EV)/(CPI×SPI) | L14: =L7+(L4-L6)/(L11*L10) -> 1007341.5 | N14: Schedule pressure also drives cost
A15: 11 | B15: 46283 | C15: 211700 | D15: 199115 | E15: 207185 | F15: =D15-C15 -> -12585 | G15: =D15-E15 -> -8070 | H15: =IF(C15=0,"",D15/C15) -> 0.94055267 | I15: =IF(E15=0,"",D15/E15) -> 0.9610493 | K15: ETC = EAC − AC | L15: =L12-L7 -> 708623.93 | N15: Cost to finish (typical)
A16: 12 | B16: 46290 | C16: 242800 | D16: 221830 | E16: 231730 | F16: =D16-C16 -> -20970 | G16: =D16-E16 -> -9900 | H16: =IF(C16=0,"",D16/C16) -> 0.91363262 | I16: =IF(E16=0,"",D16/E16) -> 0.95727787 | K16: VAC = BAC − EAC | L16: =L4-L12 -> -40173.926 | N16: Forecast overrun (typical)
A17: 13 | B17: 46297 | C17: 269700 | K17: TCPI = (BAC − EV)/(BAC − AC) | L17: =(L4-L6)/(L4-L7) -> 1.0148104 | N17: > 1 = must work more efficiently
A18: 14 | B18: 46304 | C18: 293660 | K18: % complete (EV / BAC) | L18: =L6/L4 -> 0.24642849 | N18: Physical progress
A19: 15 | B19: 46311 | C19: 321370 | K19: % planned (PV / BAC) | L19: =L5/L4 -> 0.26972383 | N19: Where we should be
A20: 16 | B20: 46318 | C20: 352920 | K20: Contingency reserve | L20: =Contingency -> 90750 | N20: Covers VAC?
A21: 17 | B21: 46325 | C21: 395130 | K21: EAC within BAC + contingency? | L21: =IF(L12<=L4+L20,"Yes","No") -> Yes | N21: Funding test for the recommendation
A22: 18 | B22: 46332 | C22: 437130
A23: 19 | B23: 46339 | C23: 465600
A24: 20 | B24: 46346 | C24: 490850 | K24: RAG thresholds: ≥ 0.95 Green · 0.90–0.95 Amber · < 0.90 Red (agreed with sponsor).
A25: 21 | B25: 46353 | C25: 505780 | K25: Check: weekly status row equals task totals | L25: =IF(AND(ABS(C16-L5)<1,ABS(D16-L6)<1,ABS(E16-L7)<1),"OK","MISMATCH") -> OK
A26: 22 | B26: 46360 | C26: 526210
A27: 23 | B27: 46367 | C27: 546640
A28: 24 | B28: 46374 | C28: 558110
A29: 25 | B29: 46381 | C29: 564860
A30: 26 | B30: 46388 | C30: 564860
A31: 27 | B31: 46395 | C31: 576510
A32: 28 | B32: 46402 | C32: 679040
A33: 29 | B33: 46409 | C33: 827910
A34: 30 | B34: 46416 | C34: 840110
A35: 31 | B35: 46423 | C35: 855360
A36: 32 | B36: 46430 | C36: 870610
A37: 33 | B37: 46437 | C37: 884480
... A40: 36 | B40: 46458 | C40: 900180

Sheet Stakeholder_Register
A1: Stakeholder register & power–interest classification
A2: Quadrant formula: power ≥ 4 and interest ≥ 4 → Manage closely; power ≥ 4 → Keep satisfied; interest ≥ 4 → Keep informed; else Monitor
A4: ID | B4: Stakeholder | C4: Role | D4: Power (1–5) | E4: Interest (1–5) | F4: Quadrant (formula) | G4: Reason for classification | H4: Current attitude | I4: Desired attitude | J4: Engagement strategy | K4: Comms ref
A5: S01 | B5: Deputy Vice-Chancellor (Education) | C5: Project sponsor | D5: 5 | E5: 5 | F5: =IF(AND(D5>=4,E5>=4),"Manage closely",IF(D5>=4,"Keep satisfied",IF(E5>=4,"Keep informed","Monitor"))) -> Manage closely | G5: Funds the project, chairs the steering committee and owns the go/no-go decision. | H5: Supportive | I5: Leading | J5: Fortnightly steering committee; early warning of variances; decisions requested with options. | K5: C01, C05
A6: S02 | B6: Chief Information Officer | C6: IT executive | D6: 5 | E6: 4 | F6: =IF(AND(D6>=4,E6>=4),"Manage closely",IF(D6>=4,"Keep satisfied",IF(E6>=4,"Keep informed","Monitor"))) -> Manage closely | G6: Owns IT architecture, operations and the identity platform; can reprioritise IT staff. | H6: Supportive | I6: Leading | J6: Steering committee member; architecture decisions escalated directly. | K6: C01, C02
A7: S03 | B7: Academic Registrar | C7: Data owner — student records | D7: 4 | E7: 5 | F7: =IF(AND(D7>=4,E7>=4),"Manage closely",IF(D7>=4,"Keep satisfied",IF(E7>=4,"Keep informed","Monitor"))) -> Manage closely | G7: Owns enrolment and student data; signs migration reconciliation; worried about enrolment disruption. | H7: Neutral | I7: Supportive | J7: Involve in cleansing decisions and reconciliation sign-off; privacy briefings before each migration. | K7: C01, C06
A8: S04 | B8: Faculty Deans | C8: Academic leadership | D8: 4 | E8: 3 | F8: =IF(AND(D8>=4,E8>=4),"Manage closely",IF(D8>=4,"Keep satisfied",IF(E8>=4,"Keep informed","Monitor"))) -> Keep satisfied | G8: Can escalate to the DVC and control faculty staff time, but day-to-day interest is moderate. | H8: Resistant | I8: Neutral | J8: Monthly faculty briefings; route feature requests through the CCB (CR-01). | K8: C11, C02
A9: S05 | B9: Students (domestic & international) | C9: Primary users | D9: 2 | E9: 5 | F9: =IF(AND(D9>=4,E9>=4),"Manage closely",IF(D9>=4,"Keep satisfied",IF(E9>=4,"Keep informed","Monitor"))) -> Keep informed | G9: Most affected by the change but have no formal decision rights; influence is via the SRC. | H9: Unaware | I9: Supportive | J9: Co-design via SRC, pilot, newsletters and go-live campaign; multilingual guides for international students. | K9: C04, C08
A10: S06 | B10: Student Representative Council (SRC) | C10: Student voice | D10: 3 | E10: 4 | F10: =IF(AND(D10>=4,E10>=4),"Manage closely",IF(D10>=4,"Keep satisfied",IF(E10>=4,"Keep informed","Monitor"))) -> Keep informed | G10: Speaks for students and can create reputational pressure, but has no budget or approval authority. | H10: Neutral | I10: Supportive | J10: Sprint review participation; co-design sessions; pilot champions. | K10: C03, C04
A11: S07 | B11: Academic staff | C11: Secondary users (LMS gateway) | D11: 2 | E11: 3 | F11: =IF(AND(D11>=4,E11>=4),"Manage closely",IF(D11>=4,"Keep satisfied",IF(E11>=4,"Keep informed","Monitor"))) -> Monitor | G11: Affected only via LMS links and student questions; little authority over the project. | H11: Unaware | I11: Neutral | J11: General updates through faculty briefings; quick-reference guide. | K11: C11
A12: S08 | B12: IT Service Desk | C12: Support provider | D12: 2 | E12: 4 | F12: =IF(AND(D12>=4,E12>=4),"Manage closely",IF(D12>=4,"Keep satisfied",IF(E12>=4,"Keep informed","Monitor"))) -> Keep informed | G12: Absorbs go-live ticket volume (R11) but does not approve scope or budget. | H12: Concerned | I12: Supportive | J12: Early training, knowledge base, hypercare stand-ups. | K12: C08, C09
A13: S09 | B13: Finance Office | C13: Budget & fees integration | D13: 4 | E13: 3 | F13: =IF(AND(D13>=4,E13>=4),"Manage closely",IF(D13>=4,"Keep satisfied",IF(E13>=4,"Keep informed","Monitor"))) -> Keep satisfied | G13: Releases funds and owns the fees system, but is interested mainly in cost and integration points. | H13: Neutral | I13: Supportive | J13: Monthly cost/EVM summary; CCB member for cost-affecting changes. | K13: C01, C05
A14: S10 | B14: Privacy Officer | C14: Compliance (Privacy Act/APPs) | D14: 4 | E14: 4 | F14: =IF(AND(D14>=4,E14>=4),"Manage closely",IF(D14>=4,"Keep satisfied",IF(E14>=4,"Keep informed","Monitor"))) -> Manage closely | G14: Can halt migration on privacy grounds and must approve the PIA (R03, CR-03). | H14: Cautious | I14: Supportive | J14: PIA co-owner; privacy briefing before every migration; CCB member. | K14: C06, C05
A15: S11 | B15: Accessibility Services | C15: Disability advocacy | D15: 2 | E15: 4 | F15: =IF(AND(D15>=4,E15>=4),"Manage closely",IF(D15>=4,"Keep satisfied",IF(E15>=4,"Keep informed","Monitor"))) -> Keep informed | G15: Advocates for students with disability (WCAG, R08) but has advisory, not approval, power. | H15: Neutral | I15: Supportive | J15: Prototype testing and WCAG audit review; sprint reviews. | K15: C03
A16: S12 | B16: LMS vendor | C16: Supplier — LMS API | D16: 4 | E16: 2 | F16: =IF(AND(D16>=4,E16>=4),"Manage closely",IF(D16>=4,"Keep satisfied",IF(E16>=4,"Keep informed","Monitor"))) -> Keep satisfied | G16: Controls the LMS API and SSO support (R02) through the contract, but has low interest in our timeline. | H16: Neutral | I16: Supportive | J16: Weekly vendor call; SLA escalation path via the CIO. | K16: C07
... A18: S14 | B18: TEQSA (regulator) | C18: External regulator | D18: 5 | E18: 1 | F18: =IF(AND(D18>=4,E18>=4),"Manage closely",IF(D18>=4,"Keep satisfied",IF(E18>=4,"Keep informed","Monitor"))) -> Keep satisfied | G18: Can impose conditions on the university but is only interested if student outcomes or data are compromised. | H18: Unaware | I18: Neutral | J18: Keep satisfied via the Registrar's routine compliance reporting; notify only if a material incident occurs. | K18: C10
B20: Manage closely | C20: =COUNTIF(F5:F18,B20) -> 4
B21: Keep satisfied | C21: =COUNTIF(F5:F18,B21) -> 4
B22: Keep informed | C22: =COUNTIF(F5:F18,B22) -> 5
B23: Monitor | C23: =COUNTIF(F5:F18,B23) -> 1

Sheet Comms_Plan
A1: Communication plan
A2: UniConnect — Student Portal Consolidation | Status date 25/09/2026 | Source: data/project.yaml
A4: ID | B4: Audience | C4: Information | D4: Method | E4: Frequency | F4: Owner | G4: Feedback | H4: Stakeholders served
A5: C01 | B5: Steering committee (DVC, CIO, Registrar, Finance) | C5: Status dashboard, EVM, top risks, decisions needed | D5: Meeting + dashboard PDF | E5: Fortnightly | F5: Project Manager | G5: Minutes and action log | H5: S01, S02, S03, S09
A6: C02 | B6: Sponsor, CIO, Deans, Privacy Officer | C6: Weekly status report (RAG, SPI/CPI, issues) | D6: Email report | E6: Weekly (Friday) | F6: Project Manager | G6: Reply/queries to PM | H6: S02, S04
A7: C03 | B7: Registrar's team, SRC, Accessibility Services | C7: Sprint demo of working features | D7: Sprint review (hybrid meeting) | E7: Every 2 weeks | F7: Development Lead | G7: Backlog items raised in Trello | H7: S06, S11
A8: C04 | B8: Students | C8: What is changing, when, pilot invitations | D8: Newsletter, portal banner, social media | E8: Monthly; weekly from Dec | F8: Change & Training Lead | G8: Survey and SRC channel | H8: S05, S06
A9: C05 | B9: Change Control Board | C9: Change requests with impact analysis | D9: CCB meeting | E9: Fortnightly or ad hoc | F9: Project Manager | G9: Decision recorded in change log | H9: S01, S09, S10
A10: C06 | B10: Privacy Officer, Registrar | C10: Migration controls, masking, reconciliation results | D10: Privacy briefing | E10: Before each migration run | F10: Data Engineer | G10: Written approval to proceed | H10: S03, S10
A11: C07 | B11: LMS vendor, portal platform vendor | C11: Integration defects, API changes, SLAs | D11: Vendor call | E11: Weekly | F11: Solution Architect | G11: Joint defect log | H11: S12, S13
A12: C08 | B12: Students, staff, IT Service Desk | C12: Go-live comms pack: how to log in, where to get help | D12: Email, intranet, FAQs, posters | E12: 4 weeks, 1 week and day 0 before go-live | F12: Change & Training Lead | G12: Help-page analytics, tickets | H12: S05, S08
A13: C09 | B13: IT Service Desk, Dev, Data Engineer | C13: Incidents, ticket trends, fixes | D13: Stand-up (15 min) | E13: Daily during hypercare | F13: Project Manager | G13: Incident log | H13: S08
A14: C10 | B14: TEQSA (via Registrar) | C14: Compliance summary; material incidents only | D14: Formal report | E14: Quarterly / as required | F14: Academic Registrar | G14: Regulator correspondence | H14: S14
A15: C11 | B15: Faculty Deans, academic staff | C15: Scope, dates, pilot, LMS link changes | D15: Faculty briefing | E15: Monthly | F15: Project Manager | G15: Q&A; requests routed to CCB | H15: S04, S07

Sheet RACI
A1: RACI matrix
A2: Exactly one A (Accountable) per deliverable — checked by formula
A4: Deliverable | B4: WBS | C4: Sponsor | D4: Project Manager | E4: Business Analyst | F4: Solution Architect | G4: Development Lead | H4: Data Engineer | I4: Test Lead | J4: UX Designer | K4: Change & Training Lead | L4: Privacy Officer | M4: A count | N4: Check
A5: Project charter | B5: 1.1 | C5: A | D5: R | E5: C | F5: I | G5: I | H5: I | I5: I | J5: I | K5: I | L5: C | M5: =COUNTIF(C5:L5,"A") -> 1 | N5: =IF(COUNTIF(C5:L5,"A")=1,"OK","FIX") -> OK
A6: PM plan & baselines / monitoring & control | B6: 1.2, 1.3 | C6: I | D6: A | E6: R | F6: C | G6: C | H6: C | I6: C | J6: I | K6: C | L6: I | M6: =COUNTIF(C6:L6,"A") -> 1 | N6: =IF(COUNTIF(C6:L6,"A")=1,"OK","FIX") -> OK
A7: Requirements & audit | B7: 2.1, 2.2 | C7: I | D7: C | E7: A | F7: C | G7: C | H7: R | I7: I | J7: R | K7: C | L7: C | M7: =COUNTIF(C7:L7,"A") -> 1 | N7: =IF(COUNTIF(C7:L7,"A")=1,"OK","FIX") -> OK
A8: Solution & SSO architecture | B8: 2.3 | C8: I | D8: C | E8: C | F8: A | G8: R | H8: C | I8: I | J8: C | K8: I | L8: C | M8: =COUNTIF(C8:L8,"A") -> 1 | N8: =IF(COUNTIF(C8:L8,"A")=1,"OK","FIX") -> OK
A9: Privacy Impact Assessment | B9: 2.4 | C9: I | D9: C | E9: R | F9: C | G9: I | H9: C | I9: I | J9: I | K9: I | L9: A | M9: =COUNTIF(C9:L9,"A") -> 1 | N9: =IF(COUNTIF(C9:L9,"A")=1,"OK","FIX") -> OK
A10: UX prototype & accessibility | B10: 2.5, 5.3 | C10: I | D10: I | E10: C | F10: I | G10: C | H10: I | I10: R | J10: A | K10: C | L10: I | M10: =COUNTIF(C10:L10,"A") -> 1 | N10: =IF(COUNTIF(C10:L10,"A")=1,"OK","FIX") -> OK
A11: Portal features (Sprints 1–4) & configuration | B11: 3.1, 3.2, 3.3, 3.4, 3.6 | C11: I | D11: C | E11: R | F11: C | G11: A | H11: I | I11: R | J11: R | K11: I | L11: I | M11: =COUNTIF(C11:L11,"A") -> 1 | N11: =IF(COUNTIF(C11:L11,"A")=1,"OK","FIX") -> OK
A12: Integration APIs & load testing | B12: 3.5, 5.4 | C12: I | D12: I | E12: C | F12: A | G12: R | H12: C | I12: R | J12: I | K12: I | L12: I | M12: =COUNTIF(C12:L12,"A") -> 1 | N12: =IF(COUNTIF(C12:L12,"A")=1,"OK","FIX") -> OK
A13: Data migration (mapping, trials, final) | B13: 4.1, 4.2, 4.3, 4.4 | C13: I | D13: C | E13: R | F13: C | G13: C | H13: A | I13: R | J13: I | K13: I | L13: C | M13: =COUNTIF(C13:L13,"A") -> 1 | N13: =IF(COUNTIF(C13:L13,"A")=1,"OK","FIX") -> OK
A14: Testing (SIT, security, UAT, regression) | B14: 5.1, 5.2, 5.5, 5.6 | C14: I | D14: C | E14: R | F14: C | G14: R | H14: C | I14: A | J14: C | K14: C | L14: C | M14: =COUNTIF(C14:L14,"A") -> 1 | N14: =IF(COUNTIF(C14:L14,"A")=1,"OK","FIX") -> OK
A15: Training, pilot & go-live cutover | B15: 6.1, 6.2, 6.3 | C15: C | D15: A | E15: C | F15: R | G15: R | H15: R | I15: C | J15: I | K15: R | L15: I | M15: =COUNTIF(C15:L15,"A") -> 1 | N15: =IF(COUNTIF(C15:L15,"A")=1,"OK","FIX") -> OK
A16: Hypercare, decommissioning & closure | B16: 6.4, 6.5, 1.4 | C16: C | D16: A | E16: R | F16: R | G16: R | H16: R | I16: C | J16: I | K16: R | L16: C | M16: =COUNTIF(C16:L16,"A") -> 1 | N16: =IF(COUNTIF(C16:L16,"A")=1,"OK","FIX") -> OK
A18: R = Responsible · A = Accountable (one per row) · C = Consulted · I = Informed

Sheet Quality_Metrics
A1: Quality metrics
A2: UniConnect — Student Portal Consolidation | Status date 25/09/2026 | Source: data/project.yaml
A4: ID | B4: Metric | C4: Target | D4: Measurement method | E4: Frequency | F4: Owner | G4: Current value | H4: RAG | I4: WBS
A5: Q01 | B5: Migration record accuracy | C5: ≥ 99.5% reconciled | D5: Automated reconciliation report vs source counts | E5: Each trial run | F5: Data Engineer | G5: 95.3% (trial 1) | H5: Red | I5: 4.3
A6: Q02 | B6: Portal availability | C6: ≥ 99.5% | D6: Uptime monitoring | E6: Monthly | F6: Solution Architect | G6: 99.2% (test env.) | H6: Amber | I6: 6.4
A7: Q03 | B7: Page load p95 at 5,000 concurrent users | C7: < 2 s | D7: Load test tool (5.4) | E7: Load test + go-live | F7: Solution Architect | G7: Not yet tested | H7: Grey | I7: 5.4
A8: Q04 | B8: WCAG 2.1 AA critical failures | C8: 0 | D8: Automated scan each sprint + audit | E8: Each sprint | F8: UX Designer | G8: 2 (Sprint 1 scan) | H8: Amber | I8: 5.3
A9: Q05 | B9: UAT pass rate | C9: ≥ 95% | D9: UAT scripts passed / executed | E9: Daily in UAT | F9: Test Lead | G9: Not started | H9: Grey | I9: 5.5
A10: Q06 | B10: Open Severity-1 defects at go-live | C10: 0 | D10: Defect tracker | E10: Weekly | F10: Test Lead | G10: 1 open (ISS-02) | H10: Amber | I10: 5.6
A11: Q07 | B11: Portal-related helpdesk tickets | C11: −30% within 3 months | D11: Service Desk reports vs 4,200/month baseline | E11: Monthly after go-live | F11: Change & Training Lead | G11: Baseline 4,200/month | H11: Grey | I11: 6.4

Sheet Control_Chart
A1: Control chart — defects logged per week
A2: Mean and σ from the stable baseline period (weeks 3–11); UCL = mean + 3σ; LCL = max(0, mean − 3σ)
A4: Week | B4: Week ending | C4: Defects | D4: Mean | E4: UCL | F4: LCL | G4: Out of control? | I4: Baseline mean | J4: =AVERAGE(C5:C13) -> 6
A5: 3 | B5: 46227 | C5: 6 | D5: =$J$4 -> 6 | E5: =$J$6 -> 9.6742346 | F5: =$J$7 -> 2.3257654 | G5: =IF(OR(C5>E5,C5<F5),"YES — investigate","No") -> No | I5: Baseline σ (sample) | J5: =STDEV(C5:C13) -> 1.2247449
A6: 4 | B6: 46234 | C6: 5 | D6: =$J$4 -> 6 | E6: =$J$6 -> 9.6742346 | F6: =$J$7 -> 2.3257654 | G6: =IF(OR(C6>E6,C6<F6),"YES — investigate","No") -> No | I6: UCL | J6: =J4+3*J5 -> 9.6742346
A7: 5 | B7: 46241 | C7: 7 | D7: =$J$4 -> 6 | E7: =$J$6 -> 9.6742346 | F7: =$J$7 -> 2.3257654 | G7: =IF(OR(C7>E7,C7<F7),"YES — investigate","No") -> No | I7: LCL | J7: =MAX(0,J4-3*J5) -> 2.3257654
A8: 6 | B8: 46248 | C8: 4 | D8: =$J$4 -> 6 | E8: =$J$6 -> 9.6742346 | F8: =$J$7 -> 2.3257654 | G8: =IF(OR(C8>E8,C8<F8),"YES — investigate","No") -> No
A9: 7 | B9: 46255 | C9: 6 | D9: =$J$4 -> 6 | E9: =$J$6 -> 9.6742346 | F9: =$J$7 -> 2.3257654 | G9: =IF(OR(C9>E9,C9<F9),"YES — investigate","No") -> No
A10: 8 | B10: 46262 | C10: 5 | D10: =$J$4 -> 6 | E10: =$J$6 -> 9.6742346 | F10: =$J$7 -> 2.3257654 | G10: =IF(OR(C10>E10,C10<F10),"YES — investigate","No") -> No
A11: 9 | B11: 46269 | C11: 8 | D11: =$J$4 -> 6 | E11: =$J$6 -> 9.6742346 | F11: =$J$7 -> 2.3257654 | G11: =IF(OR(C11>E11,C11<F11),"YES — investigate","No") -> No
A12: 10 | B12: 46276 | C12: 6 | D12: =$J$4 -> 6 | E12: =$J$6 -> 9.6742346 | F12: =$J$7 -> 2.3257654 | G12: =IF(OR(C12>E12,C12<F12),"YES — investigate","No") -> No
A13: 11 | B13: 46283 | C13: 7 | D13: =$J$4 -> 6 | E13: =$J$6 -> 9.6742346 | F13: =$J$7 -> 2.3257654 | G13: =IF(OR(C13>E13,C13<F13),"YES — investigate","No") -> No
A14: 12 | B14: 46290 | C14: 14 | D14: =$J$4 -> 6 | E14: =$J$6 -> 9.6742346 | F14: =$J$7 -> 2.3257654 | G14: =IF(OR(C14>E14,C14<F14),"YES — investigate","No") -> YES — investigate
A17: Interpretation: Week 12 (14 defects) is above the UCL: a special cause, traced to duplicate records in trial migration 1 (ISS-01), not random variation. Action: root-cause analysis and CR-02.

Sheet Change_Log
A1: Change log (CCB decisions)
A2: UniConnect — Student Portal Consolidation | Status date 25/09/2026 | Source: data/project.yaml
A4: CR | B4: Date | C4: Requester | D4: Description | E4: WBS affected | F4: Risks / issues | G4: Scope impact | H4: Schedule impact | I4: Cost impact | J4: Risk impact | K4: CCB decision | L4: CCB date | M4: Rationale | N4: Baseline updated | O4: Artefacts updated
A5: CR-01 | B5: 46260 | C5: Faculty of Business (Dean) | D5: Add mobile push notifications for timetable and fee reminders. | E5: 3.2, 3.6 | F5: R06, ISS-03 | G5: New feature + native app work (out of scope) | H5: +10 working days on Sprint 2/3 (critical-path pressure) | I5: +$42,000 | J5: Raises R06 and R05 | K5: Deferred | L5: 46267 | M5: Scope creep; would consume float and threaten go-live. Added to Phase 2 backlog. Email notifications (3.6) cover the need. | N5: No | O5: Change log, Phase 2 backlog (Trello), comms to Deans (C11)
A6: CR-02 | B6: 46289 | C6: Data Engineer / Project Manager | D6: Add a data-cleansing mini-sprint and a 3-week contract data engineer to recover trial migration 1 (response to ISS-01). | E6: 4.2, 4.3 | F6: R01, R04, ISS-01 | G6: No change to product scope; adds cleansing activity | H6: Recovers about 8 of the 10 forecast slip days (crashing 4.2/4.3 + fast-tracking SIT preparation) | I6: +$23,800 (contractor $15,600 + internal effort $8,200) from contingency reserve | J6: Reduces R01 and R04; small new onboarding risk | K6: Approved | L6: 46290 | M6: Protects the critical path and hard go-live deadline; cost is within the R01 contingency allocation ($39,000). | N6: Yes — cost baseline +$23,800 (contingency drawdown); schedule re-baselined as Baseline 1 from 28 Sep | O6: Change log, cost baseline, ProjectLibre schedule, risk register (R01), Trello [4.2]/[4.3], status report
A7: CR-03 | B7: 46275 | C7: Privacy Officer | D7: Make multi-factor authentication (MFA) mandatory for all students, not only staff. | E7: 3.1, 6.1 | F7: R03, R11, ISS-05 | G7: Small: MFA enrolment flow + help content | H7: +2 days in Sprint 2 (absorbed by float) | I7: +$4,200 | J7: Reduces R03; slightly raises R11 (MFA help tickets) | K7: Approved | L7: 46281 | M7: Compliance with APP 11 'reasonable steps'; low cost; uses float not critical path. | N7: Yes — scope statement and Sprint 2 backlog | O7: Scope statement, Trello Sprint 2 cards, training plan (6.1), risk register

Sheet Issue_Log
A1: Issue log
A2: UniConnect — Student Portal Consolidation | Status date 25/09/2026 | Source: data/project.yaml
A4: Issue | B4: Date | C4: Description | D4: Linked risk | E4: WBS | F4: Impact | G4: Owner | H4: Corrective action | I4: Due | J4: Status | K4: Days open
A5: ISS-01 | B5: 46287 | C5: Trial migration 1 found 4.7% duplicate student records (≈ 1,130 of 24,000). | D5: R01 | E5: 4.2 | F5: Critical task 4.2 behind plan; forecast go-live slips about 10 working days without action. | G5: Data Engineer | H5: CR-02 cleansing mini-sprint + contractor; Registrar decides merge rules within 2 days. | I5: 46311 | J5: Open — in progress | K5: =IF(LEFT(J5,6)="Closed","",DATE(2026,9,25)-B5) -> 3
A6: ISS-02 | B6: 46280 | C6: LMS vendor SSO token-refresh defect breaks session after 60 minutes. | D6: R02 | E6: 3.5 | F6: 3.5 at 60% vs 100% planned; uses part of its 20 days float. | G6: Solution Architect | H6: Vendor patch escalated via CIO (C07); workaround: shorter token lifetime. | I6: 46297 | J6: Open | K6: =IF(LEFT(J6,6)="Closed","",DATE(2026,9,25)-B6) -> 10
A7: ISS-03 | B7: 46260 | C7: Faculty of Business requested push notifications mid-sprint. | D7: R06 | E7: 3.2 | F7: Potential scope creep | G7: Project Manager | H7: Raised CR-01; CCB deferred to Phase 2. | I7: 46267 | J7: Closed | K7: =IF(LEFT(J7,6)="Closed","",DATE(2026,9,25)-B7)
A8: ISS-04 | B8: 46276 | C8: Sprint 1 accessibility scan: 2 critical colour-contrast failures. | D8: R08 | E8: 3.1 | F8: WCAG metric Q04 amber | G8: UX Designer | H8: Fix in Sprint 2 via design-system tokens; re-scan. | I8: 46297 | J8: In progress | K8: =IF(LEFT(J8,6)="Closed","",DATE(2026,9,25)-B8) -> 14
A9: ISS-05 | B9: 46273 | C9: Privacy Officer requires MFA for all students after PIA review. | D9: R03 | E9: 2.4 | F9: Scope change | G9: Privacy Officer | H9: Raised CR-03; approved by CCB. | I9: 46281 | J9: Closed | K9: =IF(LEFT(J9,6)="Closed","",DATE(2026,9,25)-B9)
A11: Open issues | B11: =COUNTIF(J5:J9,"Open*")+COUNTIF(J5:J9,"In progress*") -> 3

Sheet Traceability
A1: Traceability matrix — one WBS ID across every tool
A2: UniConnect — Student Portal Consolidation | Status date 25/09/2026 | Source: data/project.yaml
A4: WBS | B4: Work package | C4: ProjectLibre ID | D4: Trello card | E4: Trello link | F4: Baseline cost | G4: Linked risks | H4: RACI accountable | I4: Quality metric | J4: Critical path
A5: 1.1 | B5: Initiation & charter | C5: =VLOOKUP(A5,Schedule_WBS!$A:$E,5,FALSE()) -> 1 | D5: [1.1] Initiation & charter | E5: =HYPERLINK("https://trello.com/c/w6wkNBpd","https://trello.com/c/w6wkNBpd") -> https://trello.com/c/w6wkNBpd | F5: =VLOOKUP(A5,Schedule_WBS!$A:$N,14,FALSE()) -> 13400 | G5: — | H5: =VLOOKUP(A5,Schedule_WBS!$A:$T,20,FALSE()) -> Sponsor | I5: — | J5: =VLOOKUP(A5,Schedule_WBS!$A:$K,11,FALSE()) -> Yes
A6: 1.2 | B6: Planning & baselines | C6: =VLOOKUP(A6,Schedule_WBS!$A:$E,5,FALSE()) -> 3 | D6: [1.2] Planning & baselines | E6: =HYPERLINK("https://trello.com/c/Ftqc11da","https://trello.com/c/Ftqc11da") -> https://trello.com/c/Ftqc11da | F6: =VLOOKUP(A6,Schedule_WBS!$A:$N,14,FALSE()) -> 12960 | G6: — | H6: =VLOOKUP(A6,Schedule_WBS!$A:$T,20,FALSE()) -> Project Manager | I6: — | J6: =VLOOKUP(A6,Schedule_WBS!$A:$K,11,FALSE()) -> No
A7: 1.3 | B7: Monitoring, control & CCB | C7: =VLOOKUP(A7,Schedule_WBS!$A:$E,5,FALSE()) -> 4 | D7: [1.3] Monitoring, control & CCB | E7: =HYPERLINK("https://trello.com/c/swANm99l","https://trello.com/c/swANm99l") -> https://trello.com/c/swANm99l | F7: =VLOOKUP(A7,Schedule_WBS!$A:$N,14,FALSE()) -> 92460 | G7: — | H7: =VLOOKUP(A7,Schedule_WBS!$A:$T,20,FALSE()) -> Project Manager | I7: — | J7: =VLOOKUP(A7,Schedule_WBS!$A:$K,11,FALSE()) -> No
A8: 1.4 | B8: Closure | C8: =VLOOKUP(A8,Schedule_WBS!$A:$E,5,FALSE()) -> 5 | D8: [1.4] Closure | E8: =HYPERLINK("https://trello.com/c/JL0qAVPk","https://trello.com/c/JL0qAVPk") -> https://trello.com/c/JL0qAVPk | F8: =VLOOKUP(A8,Schedule_WBS!$A:$N,14,FALSE()) -> 6700 | G8: — | H8: =VLOOKUP(A8,Schedule_WBS!$A:$T,20,FALSE()) -> Project Manager | I8: — | J8: =VLOOKUP(A8,Schedule_WBS!$A:$K,11,FALSE()) -> Yes
A9: 2.1 | B9: Current-state portal audit | C9: =VLOOKUP(A9,Schedule_WBS!$A:$E,5,FALSE()) -> 7 | D9: [2.1] Current-state portal audit | E9: =HYPERLINK("https://trello.com/c/gKHXQBHA","https://trello.com/c/gKHXQBHA") -> https://trello.com/c/gKHXQBHA | F9: =VLOOKUP(A9,Schedule_WBS!$A:$N,14,FALSE()) -> 14800 | G9: — | H9: =VLOOKUP(A9,Schedule_WBS!$A:$T,20,FALSE()) -> Business Analyst | I9: — | J9: =VLOOKUP(A9,Schedule_WBS!$A:$K,11,FALSE()) -> Yes
A10: 2.2 | B10: Requirements workshops | C10: =VLOOKUP(A10,Schedule_WBS!$A:$E,5,FALSE()) -> 8 | D10: [2.2] Requirements workshops | E10: =HYPERLINK("https://trello.com/c/1vNe1AZp","https://trello.com/c/1vNe1AZp") -> https://trello.com/c/1vNe1AZp | F10: =VLOOKUP(A10,Schedule_WBS!$A:$N,14,FALSE()) -> 15600 | G10: R06 | H10: =VLOOKUP(A10,Schedule_WBS!$A:$T,20,FALSE()) -> Business Analyst | I10: — | J10: =VLOOKUP(A10,Schedule_WBS!$A:$K,11,FALSE()) -> Yes
A11: 2.3 | B11: Solution & SSO architecture | C11: =VLOOKUP(A11,Schedule_WBS!$A:$E,5,FALSE()) -> 9 | D11: [2.3] Solution & SSO architecture | E11: =HYPERLINK("https://trello.com/c/AuYqG8s9","https://trello.com/c/AuYqG8s9") -> https://trello.com/c/AuYqG8s9 | F11: =VLOOKUP(A11,Schedule_WBS!$A:$N,14,FALSE()) -> 18600 | G11: R02, R12 | H11: =VLOOKUP(A11,Schedule_WBS!$A:$T,20,FALSE()) -> Solution Architect | I11: — | J11: =VLOOKUP(A11,Schedule_WBS!$A:$K,11,FALSE()) -> Yes
A12: 2.4 | B12: Privacy Impact Assessment | C12: =VLOOKUP(A12,Schedule_WBS!$A:$E,5,FALSE()) -> 10 | D12: [2.4] Privacy Impact Assessment | E12: =HYPERLINK("https://trello.com/c/pjgrHDND","https://trello.com/c/pjgrHDND") -> https://trello.com/c/pjgrHDND | F12: =VLOOKUP(A12,Schedule_WBS!$A:$N,14,FALSE()) -> 10200 | G12: R03 | H12: =VLOOKUP(A12,Schedule_WBS!$A:$T,20,FALSE()) -> Privacy Officer | I12: — | J12: =VLOOKUP(A12,Schedule_WBS!$A:$K,11,FALSE()) -> No
A13: 2.5 | B13: UX & accessibility prototype | C13: =VLOOKUP(A13,Schedule_WBS!$A:$E,5,FALSE()) -> 11 | D13: [2.5] UX & accessibility prototype | E13: =HYPERLINK("https://trello.com/c/2hhm9pSY","https://trello.com/c/2hhm9pSY") -> https://trello.com/c/2hhm9pSY | F13: =VLOOKUP(A13,Schedule_WBS!$A:$N,14,FALSE()) -> 17700 | G13: R08 | H13: =VLOOKUP(A13,Schedule_WBS!$A:$T,20,FALSE()) -> UX Designer | I13: — | J13: =VLOOKUP(A13,Schedule_WBS!$A:$K,11,FALSE()) -> No
A14: 3.1 | B14: Sprint 1 SSO & dashboard | C14: =VLOOKUP(A14,Schedule_WBS!$A:$E,5,FALSE()) -> 13 | D14: [3.1] Sprint 1 SSO & dashboard | E14: =HYPERLINK("https://trello.com/c/sG9i1E50","https://trello.com/c/sG9i1E50") -> https://trello.com/c/sG9i1E50 | F14: =VLOOKUP(A14,Schedule_WBS!$A:$N,14,FALSE()) -> 29300 | G14: R02, R05, R12 | H14: =VLOOKUP(A14,Schedule_WBS!$A:$T,20,FALSE()) -> Development Lead | I14: — | J14: =VLOOKUP(A14,Schedule_WBS!$A:$K,11,FALSE()) -> No
A15: 3.2 | B15: Sprint 2 Enrolment & timetable | C15: =VLOOKUP(A15,Schedule_WBS!$A:$E,5,FALSE()) -> 14 | D15: [3.2] Sprint 2 Enrolment & timetable | E15: =HYPERLINK("https://trello.com/c/Oys71NKi","https://trello.com/c/Oys71NKi") -> https://trello.com/c/Oys71NKi | F15: =VLOOKUP(A15,Schedule_WBS!$A:$N,14,FALSE()) -> 29300 | G15: R05, R06 | H15: =VLOOKUP(A15,Schedule_WBS!$A:$T,20,FALSE()) -> Development Lead | I15: — | J15: =VLOOKUP(A15,Schedule_WBS!$A:$K,11,FALSE()) -> No
A16: 3.3 | B16: Sprint 3 Fees & payments | C16: =VLOOKUP(A16,Schedule_WBS!$A:$E,5,FALSE()) -> 15 | D16: [3.3] Sprint 3 Fees & payments | E16: =HYPERLINK("https://trello.com/c/krHnWWTM","https://trello.com/c/krHnWWTM") -> https://trello.com/c/krHnWWTM | F16: =VLOOKUP(A16,Schedule_WBS!$A:$N,14,FALSE()) -> 29300 | G16: R05, R06 | H16: =VLOOKUP(A16,Schedule_WBS!$A:$T,20,FALSE()) -> Development Lead | I16: — | J16: =VLOOKUP(A16,Schedule_WBS!$A:$K,11,FALSE()) -> No
A17: 3.4 | B17: Sprint 4 Services & helpdesk | C17: =VLOOKUP(A17,Schedule_WBS!$A:$E,5,FALSE()) -> 16 | D17: [3.4] Sprint 4 Services & helpdesk | E17: =HYPERLINK("https://trello.com/c/fhyGOG3V","https://trello.com/c/fhyGOG3V") -> https://trello.com/c/fhyGOG3V | F17: =VLOOKUP(A17,Schedule_WBS!$A:$N,14,FALSE()) -> 29300 | G17: R05, R06 | H17: =VLOOKUP(A17,Schedule_WBS!$A:$T,20,FALSE()) -> Development Lead | I17: — | J17: =VLOOKUP(A17,Schedule_WBS!$A:$K,11,FALSE()) -> No
A18: 3.5 | B18: Integration APIs (SIS, LMS, Finance) | C18: =VLOOKUP(A18,Schedule_WBS!$A:$E,5,FALSE()) -> 17 | D18: [3.5] Integration APIs (SIS, LMS, Finance) | E18: =HYPERLINK("https://trello.com/c/k2OzKmNi","https://trello.com/c/k2OzKmNi") -> https://trello.com/c/k2OzKmNi | F18: =VLOOKUP(A18,Schedule_WBS!$A:$N,14,FALSE()) -> 28000 | G18: R02 | H18: =VLOOKUP(A18,Schedule_WBS!$A:$T,20,FALSE()) -> Solution Architect | I18: — | J18: =VLOOKUP(A18,Schedule_WBS!$A:$K,11,FALSE()) -> No
A19: 3.6 | B19: Content & notifications configuration | C19: =VLOOKUP(A19,Schedule_WBS!$A:$E,5,FALSE()) -> 18 | D19: [3.6] Content & notifications configuration | E19: =HYPERLINK("https://trello.com/c/QfSYD0i1","https://trello.com/c/QfSYD0i1") -> https://trello.com/c/QfSYD0i1 | F19: =VLOOKUP(A19,Schedule_WBS!$A:$N,14,FALSE()) -> 5600 | G19: — | H19: =VLOOKUP(A19,Schedule_WBS!$A:$T,20,FALSE()) -> Development Lead | I19: — | J19: =VLOOKUP(A19,Schedule_WBS!$A:$K,11,FALSE()) -> No
A20: 4.1 | B20: Data mapping & cleansing | C20: =VLOOKUP(A20,Schedule_WBS!$A:$E,5,FALSE()) -> 20 | D20: [4.1] Data mapping & cleansing | E20: =HYPERLINK("https://trello.com/c/4bcpHzbS","https://trello.com/c/4bcpHzbS") -> https://trello.com/c/4bcpHzbS | F20: =VLOOKUP(A20,Schedule_WBS!$A:$N,14,FALSE()) -> 12600 | G20: R01 | H20: =VLOOKUP(A20,Schedule_WBS!$A:$T,20,FALSE()) -> Data Engineer | I20: — | J20: =VLOOKUP(A20,Schedule_WBS!$A:$K,11,FALSE()) -> Yes
A21: 4.2 | B21: Migration scripts & trial migration 1 | C21: =VLOOKUP(A21,Schedule_WBS!$A:$E,5,FALSE()) -> 21 | D21: [4.2] Migration scripts & trial migration 1 | E21: =HYPERLINK("https://trello.com/c/ab8HgR9E","https://trello.com/c/ab8HgR9E") -> https://trello.com/c/ab8HgR9E | F21: =VLOOKUP(A21,Schedule_WBS!$A:$N,14,FALSE()) -> 18300 | G21: R01, R03 | H21: =VLOOKUP(A21,Schedule_WBS!$A:$T,20,FALSE()) -> Data Engineer | I21: — | J21: =VLOOKUP(A21,Schedule_WBS!$A:$K,11,FALSE()) -> Yes
A22: 4.3 | B22: Trial migration 2 & reconciliation | C22: =VLOOKUP(A22,Schedule_WBS!$A:$E,5,FALSE()) -> 22 | D22: [4.3] Trial migration 2 & reconciliation | E22: =HYPERLINK("https://trello.com/c/yqJes5HD","https://trello.com/c/yqJes5HD") -> https://trello.com/c/yqJes5HD | F22: =VLOOKUP(A22,Schedule_WBS!$A:$N,14,FALSE()) -> 36600 | G22: R01, R03 | H22: =VLOOKUP(A22,Schedule_WBS!$A:$T,20,FALSE()) -> Data Engineer | I22: Q01 | J22: =VLOOKUP(A22,Schedule_WBS!$A:$K,11,FALSE()) -> Yes
A23: 4.4 | B23: Final migration | C23: =VLOOKUP(A23,Schedule_WBS!$A:$E,5,FALSE()) -> 24 | D23: [4.4] Final migration | E23: =HYPERLINK("https://trello.com/c/MziySy58","https://trello.com/c/MziySy58") -> https://trello.com/c/MziySy58 | F23: =VLOOKUP(A23,Schedule_WBS!$A:$N,14,FALSE()) -> 8900 | G23: R03, R04 | H23: =VLOOKUP(A23,Schedule_WBS!$A:$T,20,FALSE()) -> Data Engineer | I23: — | J23: =VLOOKUP(A23,Schedule_WBS!$A:$K,11,FALSE()) -> Yes
A24: 5.1 | B24: System integration testing | C24: =VLOOKUP(A24,Schedule_WBS!$A:$E,5,FALSE()) -> 25 | D24: [5.1] System integration testing | E24: =HYPERLINK("https://trello.com/c/lwu7yxdn","https://trello.com/c/lwu7yxdn") -> https://trello.com/c/lwu7yxdn | F24: =VLOOKUP(A24,Schedule_WBS!$A:$N,14,FALSE()) -> 34200 | G24: — | H24: =VLOOKUP(A24,Schedule_WBS!$A:$T,20,FALSE()) -> Test Lead | I24: — | J24: =VLOOKUP(A24,Schedule_WBS!$A:$K,11,FALSE()) -> Yes
A25: 5.2 | B25: Security/penetration testing | C25: =VLOOKUP(A25,Schedule_WBS!$A:$E,5,FALSE()) -> 26 | D25: [5.2] Security/penetration testing | E25: =HYPERLINK("https://trello.com/c/BEGJQGdw","https://trello.com/c/BEGJQGdw") -> https://trello.com/c/BEGJQGdw | F25: =VLOOKUP(A25,Schedule_WBS!$A:$N,14,FALSE()) -> 42000 | G25: — | H25: =VLOOKUP(A25,Schedule_WBS!$A:$T,20,FALSE()) -> Test Lead | I25: — | J25: =VLOOKUP(A25,Schedule_WBS!$A:$K,11,FALSE()) -> No
A26: 5.3 | B26: WCAG 2.1 AA audit | C26: =VLOOKUP(A26,Schedule_WBS!$A:$E,5,FALSE()) -> 27 | D26: [5.3] WCAG 2.1 AA audit | E26: =HYPERLINK("https://trello.com/c/nuDiYazQ","https://trello.com/c/nuDiYazQ") -> https://trello.com/c/nuDiYazQ | F26: =VLOOKUP(A26,Schedule_WBS!$A:$N,14,FALSE()) -> 11000 | G26: R08 | H26: =VLOOKUP(A26,Schedule_WBS!$A:$T,20,FALSE()) -> UX Designer | I26: Q04 | J26: =VLOOKUP(A26,Schedule_WBS!$A:$K,11,FALSE()) -> No
A27: 5.4 | B27: Load testing (enrolment peak) | C27: =VLOOKUP(A27,Schedule_WBS!$A:$E,5,FALSE()) -> 28 | D27: [5.4] Load testing (enrolment peak) | E27: =HYPERLINK("https://trello.com/c/QEF3XnUk","https://trello.com/c/QEF3XnUk") -> https://trello.com/c/QEF3XnUk | F27: =VLOOKUP(A27,Schedule_WBS!$A:$N,14,FALSE()) -> 9800 | G27: R07 | H27: =VLOOKUP(A27,Schedule_WBS!$A:$T,20,FALSE()) -> Solution Architect | I27: Q03 | J27: =VLOOKUP(A27,Schedule_WBS!$A:$K,11,FALSE()) -> No
A28: 5.5 | B28: User acceptance testing | C28: =VLOOKUP(A28,Schedule_WBS!$A:$E,5,FALSE()) -> 29 | D28: [5.5] User acceptance testing | E28: =HYPERLINK("https://trello.com/c/0OQxOzfu","https://trello.com/c/0OQxOzfu") -> https://trello.com/c/0OQxOzfu | F28: =VLOOKUP(A28,Schedule_WBS!$A:$N,14,FALSE()) -> 27000 | G28: — | H28: =VLOOKUP(A28,Schedule_WBS!$A:$T,20,FALSE()) -> Test Lead | I28: Q05 | J28: =VLOOKUP(A28,Schedule_WBS!$A:$K,11,FALSE()) -> Yes
A29: 5.6 | B29: Regression & defect remediation | C29: =VLOOKUP(A29,Schedule_WBS!$A:$E,5,FALSE()) -> 30 | D29: [5.6] Regression & defect remediation | E29: =HYPERLINK("https://trello.com/c/afOrVUBH","https://trello.com/c/afOrVUBH") -> https://trello.com/c/afOrVUBH | F29: =VLOOKUP(A29,Schedule_WBS!$A:$N,14,FALSE()) -> 16160 | G29: — | H29: =VLOOKUP(A29,Schedule_WBS!$A:$T,20,FALSE()) -> Test Lead | I29: Q06 | J29: =VLOOKUP(A29,Schedule_WBS!$A:$K,11,FALSE()) -> No
A30: 6.1 | B30: Training & change comms | C30: =VLOOKUP(A30,Schedule_WBS!$A:$E,5,FALSE()) -> 32 | D30: [6.1] Training & change comms | E30: =HYPERLINK("https://trello.com/c/yEbNDknS","https://trello.com/c/yEbNDknS") -> https://trello.com/c/yEbNDknS | F30: =VLOOKUP(A30,Schedule_WBS!$A:$N,14,FALSE()) -> 22400 | G30: R09, R11 | H30: =VLOOKUP(A30,Schedule_WBS!$A:$T,20,FALSE()) -> Project Manager | I30: — | J30: =VLOOKUP(A30,Schedule_WBS!$A:$K,11,FALSE()) -> No
A31: 6.2 | B31: Faculty pilot | C31: =VLOOKUP(A31,Schedule_WBS!$A:$E,5,FALSE()) -> 33 | D31: [6.2] Faculty pilot | E31: =HYPERLINK("https://trello.com/c/6RXkUi0R","https://trello.com/c/6RXkUi0R") -> https://trello.com/c/6RXkUi0R | F31: =VLOOKUP(A31,Schedule_WBS!$A:$N,14,FALSE()) -> 15800 | G31: R09, R13 | H31: =VLOOKUP(A31,Schedule_WBS!$A:$T,20,FALSE()) -> Project Manager | I31: — | J31: =VLOOKUP(A31,Schedule_WBS!$A:$K,11,FALSE()) -> Yes
A32: 6.3 | B32: Go-live cutover | C32: =VLOOKUP(A32,Schedule_WBS!$A:$E,5,FALSE()) -> 34 | D32: [6.3] Go-live cutover | E32: =HYPERLINK("https://trello.com/c/DK4Gh3k2","https://trello.com/c/DK4Gh3k2") -> https://trello.com/c/DK4Gh3k2 | F32: =VLOOKUP(A32,Schedule_WBS!$A:$N,14,FALSE()) -> 234600 | G32: R04, R07, R10 | H32: =VLOOKUP(A32,Schedule_WBS!$A:$T,20,FALSE()) -> Project Manager | I32: — | J32: =VLOOKUP(A32,Schedule_WBS!$A:$K,11,FALSE()) -> Yes
A33: 6.4 | B33: Hypercare | C33: =VLOOKUP(A33,Schedule_WBS!$A:$E,5,FALSE()) -> 36 | D33: [6.4] Hypercare | E33: =HYPERLINK("https://trello.com/c/8S47PE06","https://trello.com/c/8S47PE06") -> https://trello.com/c/8S47PE06 | F33: =VLOOKUP(A33,Schedule_WBS!$A:$N,14,FALSE()) -> 47600 | G33: R11 | H33: =VLOOKUP(A33,Schedule_WBS!$A:$T,20,FALSE()) -> Project Manager | I33: Q02, Q07 | J33: =VLOOKUP(A33,Schedule_WBS!$A:$K,11,FALSE()) -> Yes
A34: 6.5 | B34: Legacy portal decommissioning | C34: =VLOOKUP(A34,Schedule_WBS!$A:$E,5,FALSE()) -> 37 | D34: [6.5] Legacy portal decommissioning | E34: =HYPERLINK("https://trello.com/c/66UQ2c1G","https://trello.com/c/66UQ2c1G") -> https://trello.com/c/66UQ2c1G | F34: =VLOOKUP(A34,Schedule_WBS!$A:$N,14,FALSE()) -> 10000 | G34: — | H34: =VLOOKUP(A34,Schedule_WBS!$A:$T,20,FALSE()) -> Project Manager | I34: — | J34: =VLOOKUP(A34,Schedule_WBS!$A:$K,11,FALSE()) -> Yes
B36: Work packages traced | C36: =COUNTA(A5:A34) -> 30

Sheet Closure
A1: Closure checklist, benefits realisation and lessons learned
A2: UniConnect — Student Portal Consolidation | Status date 25/09/2026 | Source: data/project.yaml
A4: # | B4: Closure item | C4: Owner | D4: Status
A5: 1 | B5: All deliverables accepted against acceptance criteria | C5: Project Manager | D5: Not started
A6: 2 | B6: Registrar sign-off on final migration reconciliation | C6: Academic Registrar | D6: Not started
A7: 3 | B7: UAT, security and WCAG reports archived | C7: Test Lead | D7: Not started
A8: 4 | B8: Legacy portals decommissioned and data archived per retention schedule | C8: Solution Architect | D8: Not started
A9: 5 | B9: Privacy Officer confirms non-production data destroyed | C9: Privacy Officer | D9: Not started
A10: 6 | B10: Vendor contracts closed; contractor access revoked | C10: Finance Office | D10: Not started
A11: 7 | B11: Final cost reconciliation vs budget; unused reserves returned | C11: Project Manager | D11: Not started
A12: 8 | B12: Handover to BAU support (runbooks, knowledge base, SLAs) | C12: Development Lead | D12: Not started
A13: 9 | B13: Benefits realisation plan handed to sponsor | C13: Sponsor | D13: Not started
A14: 10 | B14: Lessons learned workshop held and register published | C14: Project Manager | D14: In progress (captured each sprint)
A15: 11 | B15: Trello board archived; ProjectLibre final actuals saved | C15: Project Manager | D15: Not started
A16: 12 | B16: Team released and recognised | C16: Project Manager | D16: Not started
A17: 13 | B17: Closure report approved by steering committee (M7) | C17: Sponsor | D17: Not started
B18: Items complete | D18: =COUNTIF(D5:D17,"Done")&" of "&COUNTA(B5:B17) -> 0 of 13
A20: Benefits realisation plan
A21: # | B21: Benefit / KPI | C21: Baseline → Target | D21: Measure date / Owner
A22: 1 | B22: Fewer helpdesk tickets — KPI: Portal-related tickets per month | C22: 4,200 → ≤ 2,940 (−30%) | D22: 30/04/2027 · IT Service Desk Manager
A23: 2 | B23: Single login — KPI: % of students using SSO + MFA | C23: 0% → ≥ 95% | D23: 31/03/2027 · CIO
A24: 3 | B24: Legacy cost savings — KPI: Annual licence + support cost of legacy portals | C24: $140k/yr → $0 after decommissioning | D24: 30/06/2027 · Finance Office
A25: 4 | B25: Data quality — KPI: Duplicate student records | C25: 4.7% (trial 1) → < 0.5% | D25: 31/03/2027 · Academic Registrar
A26: 5 | B26: Student experience — KPI: Portal satisfaction (survey, 1–5) | C26: 2.9 → ≥ 4.0 | D26: 31/05/2027 · DVC (Education)
A28: Lessons learned (what happened / impact / recommendation)
A29: ID | B29: What happened | C29: Impact | D29: Recommendation
A30: L1 | B30: Data profiling in 2.1 sampled only 5% of records. | C30: Duplicates found late (ISS-01), on the critical path. | D30: Profile 100% of keys before mapping; make data quality a gate at M2.
A31: L2 | B31: LMS SSO proof of concept ran inside Sprint 1. | C31: Token defect (ISS-02) surfaced early enough to use float. | D31: Keep technical spikes before dependent sprints.
A32: L3 | B32: Faculty feature requests arrived informally. | C32: Risk of scope creep (CR-01). | D32: Publish the CCB process in the charter and at every faculty briefing.
A33: L4 | B33: Accessibility scans ran from Sprint 1. | C33: Contrast failures fixed cheaply (ISS-04). | D33: Automate WCAG scans in the build pipeline.
A34: L5 | B34: EVM reported weekly from week 4. | C34: SPI drop visible within a week of ISS-01. | D34: Keep weekly EVM with RAG thresholds agreed by the sponsor.
A35: L6 | B35: Contingency reserve was sized from risk EMVs. | C35: CR-02 was funded without new approval. | D35: Link each reserve dollar to a named risk.
A36: L7 | B36: Privacy Officer joined the CCB. | C36: MFA decision (CR-03) made in one week. | D36: Include compliance roles on the CCB from initiation.

Sheet Schedule_WBS
A1: Schedule & WBS work packages (mirrors A2_GroupXX_ProjectLibre.pod)
A2: UniConnect — Student Portal Consolidation | Status date 25/09/2026 | Source: data/project.yaml
A4: WBS | B4: Branch | C4: Task | D4: Duration (d) | E4: PL ID | F4: Baseline start | G4: Baseline finish | H4: Forecast finish | I4: Total float (d) | J4: Forecast float (d) | K4: Critical | L4: Labour cost | M4: Fixed cost | N4: Baseline cost (BAC) | O4: Planned % at status | P4: % complete | Q4: PV | R4: EV | S4: AC (actual) | T4: Owner (RACI A)
A5: 1.1 | B5: 1 | C5: Initiation & charter | D5: 10 | E5: 1 | F5: 46209 | G5: 46220 | H5: 46220 | I5: 0 | J5: 0 | K5: =IF(I5=0,"Yes","No") -> Yes | L5: =SUMIF(Assignments!$A:$A,A5,Assignments!$G:$G) -> 13400 | M5: 0 | N5: =L5+M5 -> 13400 | O5: =IF(N5=0,1,Q5/N5) -> 1 | P5: 1 | Q5: 13400 | R5: =N5*P5 -> 13400 | S5: 13400 | T5: Sponsor
A6: M1 | B6: 1 | C6: Charter approved | D6: 0 | E6: 2 | F6: 46223 | G6: 46220 | H6: 46220 | I6: 0 | J6: 0 | K6: =IF(I6=0,"Yes","No") -> Yes | L6: =SUMIF(Assignments!$A:$A,A6,Assignments!$G:$G) -> 0 | M6: 0 | N6: =L6+M6 -> 0 | O6: =IF(N6=0,1,Q6/N6) -> 1 | P6: 1 | Q6: 0 | R6: =N6*P6 -> 0 | S6: 0 | T6: Project Manager
A7: 1.2 | B7: 1 | C7: Planning & baselines | D7: 8 | E7: 3 | F7: 46223 | G7: 46232 | H7: 46232 | I7: 2 | J7: 2 | K7: =IF(I7=0,"Yes","No") -> No | L7: =SUMIF(Assignments!$A:$A,A7,Assignments!$G:$G) -> 12960 | M7: 0 | N7: =L7+M7 -> 12960 | O7: =IF(N7=0,1,Q7/N7) -> 1 | P7: 1 | Q7: 12960 | R7: =N7*P7 -> 12960 | S7: 12960 | T7: Project Manager
A8: 1.3 | B8: 1 | C8: Monitoring, control & CCB | D8: 138 | E8: 4 | F8: 46233 | G8: 46437 | H8: 46437 | I8: 9 | J8: 19 | K8: =IF(I8=0,"Yes","No") -> No | L8: =SUMIF(Assignments!$A:$A,A8,Assignments!$G:$G) -> 92460 | M8: 0 | N8: =L8+M8 -> 92460 | O8: =IF(N8=0,0,Q8/N8) -> 0.30434783 | P8: 0.30434783 | Q8: 28140 | R8: =N8*P8 -> 28140 | S8: 28140 | T8: Project Manager
A9: 1.4 | B9: 1 | C9: Closure | D9: 5 | E9: 5 | F9: 46451 | G9: 46457 | H9: 46471 | I9: 0 | J9: 0 | K9: =IF(I9=0,"Yes","No") -> Yes | L9: =SUMIF(Assignments!$A:$A,A9,Assignments!$G:$G) -> 6700 | M9: 0 | N9: =L9+M9 -> 6700 | O9: =IF(N9=0,0,Q9/N9) -> 0 | P9: 0 | Q9: 0 | R9: =N9*P9 -> 0 | S9: 0 | T9: Project Manager
A10: M7 | B10: 1 | C10: Project closed | D10: 0 | E10: 6 | F10: 46458 | G10: 46457 | H10: 46471 | I10: 0 | J10: 0 | K10: =IF(I10=0,"Yes","No") -> Yes | L10: =SUMIF(Assignments!$A:$A,A10,Assignments!$G:$G) -> 0 | M10: 0 | N10: =L10+M10 -> 0 | O10: =IF(N10=0,0,Q10/N10) -> 0 | P10: 0 | Q10: 0 | R10: =N10*P10 -> 0 | S10: 0 | T10: Project Manager
A11: 2.1 | B11: 2 | C11: Current-state portal audit | D11: 10 | E11: 7 | F11: 46223 | G11: 46234 | H11: 46234 | I11: 0 | J11: 0 | K11: =IF(I11=0,"Yes","No") -> Yes | L11: =SUMIF(Assignments!$A:$A,A11,Assignments!$G:$G) -> 14800 | M11: 0 | N11: =L11+M11 -> 14800 | O11: =IF(N11=0,1,Q11/N11) -> 1 | P11: 1 | Q11: 14800 | R11: =N11*P11 -> 14800 | S11: 14800 | T11: Business Analyst
A12: 2.2 | B12: 2 | C12: Requirements workshops | D12: 10 | E12: 8 | F12: 46237 | G12: 46248 | H12: 46248 | I12: 0 | J12: 0 | K12: =IF(I12=0,"Yes","No") -> Yes | L12: =SUMIF(Assignments!$A:$A,A12,Assignments!$G:$G) -> 15600 | M12: 0 | N12: =L12+M12 -> 15600 | O12: =IF(N12=0,1,Q12/N12) -> 1 | P12: 1 | Q12: 15600 | R12: =N12*P12 -> 15600 | S12: 15600 | T12: Business Analyst
A13: 2.3 | B13: 2 | C13: Solution & SSO architecture | D13: 10 | E13: 9 | F13: 46251 | G13: 46262 | H13: 46262 | I13: 0 | J13: 0 | K13: =IF(I13=0,"Yes","No") -> Yes | L13: =SUMIF(Assignments!$A:$A,A13,Assignments!$G:$G) -> 18600 | M13: 0 | N13: =L13+M13 -> 18600 | O13: =IF(N13=0,1,Q13/N13) -> 1 | P13: 1 | Q13: 18600 | R13: =N13*P13 -> 18600 | S13: 22320 | T13: Solution Architect
A14: 2.4 | B14: 2 | C14: Privacy Impact Assessment | D14: 10 | E14: 10 | F14: 46258 | G14: 46269 | H14: 46269 | I14: 10 | J14: 20 | K14: =IF(I14=0,"Yes","No") -> No | L14: =SUMIF(Assignments!$A:$A,A14,Assignments!$G:$G) -> 10200 | M14: 0 | N14: =L14+M14 -> 10200 | O14: =IF(N14=0,1,Q14/N14) -> 1 | P14: 1 | Q14: 10200 | R14: =N14*P14 -> 10200 | S14: 10200 | T14: Privacy Officer
A15: 2.5 | B15: 2 | C15: UX & accessibility prototype | D15: 15 | E15: 11 | F15: 46251 | G15: 46269 | H15: 46269 | I15: 10 | J15: 20 | K15: =IF(I15=0,"Yes","No") -> No | L15: =SUMIF(Assignments!$A:$A,A15,Assignments!$G:$G) -> 17700 | M15: 0 | N15: =L15+M15 -> 17700 | O15: =IF(N15=0,1,Q15/N15) -> 1 | P15: 1 | Q15: 17700 | R15: =N15*P15 -> 17700 | S15: 17700 | T15: UX Designer
A16: M2 | B16: 2 | C16: Design sign-off | D16: 0 | E16: 12 | F16: 46272 | G16: 46269 | H16: 46269 | I16: 10 | J16: 20 | K16: =IF(I16=0,"Yes","No") -> No | L16: =SUMIF(Assignments!$A:$A,A16,Assignments!$G:$G) -> 0 | M16: 0 | N16: =L16+M16 -> 0 | O16: =IF(N16=0,1,Q16/N16) -> 1 | P16: 1 | Q16: 0 | R16: =N16*P16 -> 0 | S16: 0 | T16: Project Manager
A17: 3.1 | B17: 3 | C17: Sprint 1 SSO & dashboard | D17: 10 | E17: 13 | F17: 46265 | G17: 46276 | H17: 46276 | I17: 5 | J17: 15 | K17: =IF(I17=0,"Yes","No") -> No | L17: =SUMIF(Assignments!$A:$A,A17,Assignments!$G:$G) -> 29300 | M17: 0 | N17: =L17+M17 -> 29300 | O17: =IF(N17=0,1,Q17/N17) -> 1 | P17: 1 | Q17: 29300 | R17: =N17*P17 -> 29300 | S17: 29300 | T17: Development Lead
A18: 3.2 | B18: 3 | C18: Sprint 2 Enrolment & timetable | D18: 10 | E18: 14 | F18: 46279 | G18: 46290 | H18: 46290 | I18: 5 | J18: 15 | K18: =IF(I18=0,"Yes","No") -> No | L18: =SUMIF(Assignments!$A:$A,A18,Assignments!$G:$G) -> 29300 | M18: 0 | N18: =L18+M18 -> 29300 | O18: =IF(N18=0,1,Q18/N18) -> 1 | P18: 0.8 | Q18: 29300 | R18: =N18*P18 -> 23440 | S18: 23440 | T18: Development Lead
A19: 3.3 | B19: 3 | C19: Sprint 3 Fees & payments | D19: 10 | E19: 15 | F19: 46293 | G19: 46307 | H19: 46307 | I19: 5 | J19: 15 | K19: =IF(I19=0,"Yes","No") -> No | L19: =SUMIF(Assignments!$A:$A,A19,Assignments!$G:$G) -> 29300 | M19: 0 | N19: =L19+M19 -> 29300 | O19: =IF(N19=0,0,Q19/N19) -> 0 | P19: 0 | Q19: 0 | R19: =N19*P19 -> 0 | S19: 0 | T19: Development Lead
A20: 3.4 | B20: 3 | C20: Sprint 4 Services & helpdesk | D20: 10 | E20: 16 | F20: 46308 | G20: 46321 | H20: 46321 | I20: 5 | J20: 15 | K20: =IF(I20=0,"Yes","No") -> No | L20: =SUMIF(Assignments!$A:$A,A20,Assignments!$G:$G) -> 29300 | M20: 0 | N20: =L20+M20 -> 29300 | O20: =IF(N20=0,0,Q20/N20) -> 0 | P20: 0 | Q20: 0 | R20: =N20*P20 -> 0 | S20: 0 | T20: Development Lead
A21: 3.5 | B21: 3 | C21: Integration APIs (SIS, LMS, Finance) | D21: 20 | E21: 17 | F21: 46265 | G21: 46290 | H21: 46290 | I21: 5 | J21: 15 | K21: =IF(I21=0,"Yes","No") -> No | L21: =SUMIF(Assignments!$A:$A,A21,Assignments!$G:$G) -> 28000 | M21: 0 | N21: =L21+M21 -> 28000 | O21: =IF(N21=0,1,Q21/N21) -> 1 | P21: 0.7 | Q21: 28000 | R21: =N21*P21 -> 19600 | S21: 19600 | T21: Solution Architect
A22: 3.6 | B22: 3 | C22: Content & notifications configuration | D22: 10 | E22: 18 | F22: 46293 | G22: 46307 | H22: 46307 | I22: 15 | J22: 25 | K22: =IF(I22=0,"Yes","No") -> No | L22: =SUMIF(Assignments!$A:$A,A22,Assignments!$G:$G) -> 5600 | M22: 0 | N22: =L22+M22 -> 5600 | O22: =IF(N22=0,0,Q22/N22) -> 0 | P22: 0 | Q22: 0 | R22: =N22*P22 -> 0 | S22: 0 | T22: Development Lead
A23: M3 | B23: 3 | C23: Build complete | D23: 0 | E23: 19 | F23: 46322 | G23: 46321 | H23: 46321 | I23: 5 | J23: 15 | K23: =IF(I23=0,"Yes","No") -> No | L23: =SUMIF(Assignments!$A:$A,A23,Assignments!$G:$G) -> 0 | M23: 0 | N23: =L23+M23 -> 0 | O23: =IF(N23=0,0,Q23/N23) -> 0 | P23: 0 | Q23: 0 | R23: =N23*P23 -> 0 | S23: 0 | T23: Project Manager
A24: 4.1 | B24: 4 | C24: Data mapping & cleansing | D24: 10 | E24: 20 | F24: 46265 | G24: 46276 | H24: 46276 | I24: 0 | J24: 0 | K24: =IF(I24=0,"Yes","No") -> Yes | L24: =SUMIF(Assignments!$A:$A,A24,Assignments!$G:$G) -> 12600 | M24: 0 | N24: =L24+M24 -> 12600 | O24: =IF(N24=0,1,Q24/N24) -> 1 | P24: 1 | Q24: 12600 | R24: =N24*P24 -> 12600 | S24: 15120 | T24: Data Engineer
A25: 4.2 | B25: 4 | C25: Migration scripts & trial migration 1 | D25: 15 | E25: 21 | F25: 46279 | G25: 46297 | H25: 46314 | I25: 0 | J25: 0 | K25: =IF(I25=0,"Yes","No") -> Yes | L25: =SUMIF(Assignments!$A:$A,A25,Assignments!$G:$G) -> 18300 | M25: 0 | N25: =L25+M25 -> 18300 | O25: =IF(N25=0,0,Q25/N25) -> 0.66666667 | P25: 0.3 | Q25: 12200 | R25: =N25*P25 -> 5490 | S25: 9150 | T25: Data Engineer
A26: 4.3 | B26: 4 | C26: Trial migration 2 & reconciliation | D26: 20 | E26: 22 | F26: 46301 | G26: 46328 | H26: 46342 | I26: 0 | J26: 0 | K26: =IF(I26=0,"Yes","No") -> Yes | L26: =SUMIF(Assignments!$A:$A,A26,Assignments!$G:$G) -> 36600 | M26: 0 | N26: =L26+M26 -> 36600 | O26: =IF(N26=0,0,Q26/N26) -> 0 | P26: 0 | Q26: 0 | R26: =N26*P26 -> 0 | S26: 0 | T26: Data Engineer
A27: M4 | B27: 4 | C27: Trial migration passed | D27: 0 | E27: 23 | F27: 46329 | G27: 46328 | H27: 46342 | I27: 0 | J27: 0 | K27: =IF(I27=0,"Yes","No") -> Yes | L27: =SUMIF(Assignments!$A:$A,A27,Assignments!$G:$G) -> 0 | M27: 0 | N27: =L27+M27 -> 0 | O27: =IF(N27=0,0,Q27/N27) -> 0 | P27: 0 | Q27: 0 | R27: =N27*P27 -> 0 | S27: 0 | T27: Project Manager
A28: 4.4 | B28: 4 | C28: Final migration | D28: 5 | E28: 24 | F28: 46394 | G28: 46400 | H28: 46415 | I28: 0 | J28: 0 | K28: =IF(I28=0,"Yes","No") -> Yes | L28: =SUMIF(Assignments!$A:$A,A28,Assignments!$G:$G) -> 8900 | M28: 0 | N28: =L28+M28 -> 8900 | O28: =IF(N28=0,0,Q28/N28) -> 0 | P28: 0 | Q28: 0 | R28: =N28*P28 -> 0 | S28: 0 | T28: Data Engineer
A29: 5.1 | B29: 5 | C29: System integration testing | D29: 15 | E29: 25 | F29: 46329 | G29: 46349 | H29: 46363 | I29: 0 | J29: 0 | K29: =IF(I29=0,"Yes","No") -> Yes | L29: =SUMIF(Assignments!$A:$A,A29,Assignments!$G:$G) -> 34200 | M29: 0 | N29: =L29+M29 -> 34200 | O29: =IF(N29=0,0,Q29/N29) -> 0 | P29: 0 | Q29: 0 | R29: =N29*P29 -> 0 | S29: 0 | T29: Test Lead
A30: 5.2 | B30: 5 | C30: Security/penetration testing | D30: 10 | E30: 26 | F30: 46322 | G30: 46335 | H30: 46335 | I30: 25 | J30: 35 | K30: =IF(I30=0,"Yes","No") -> No | L30: =SUMIF(Assignments!$A:$A,A30,Assignments!$G:$G) -> 17000 | M30: 25000 | N30: =L30+M30 -> 42000 | O30: =IF(N30=0,0,Q30/N30) -> 0 | P30: 0 | Q30: 0 | R30: =N30*P30 -> 0 | S30: 0 | T30: Test Lead
A31: 5.3 | B31: 5 | C31: WCAG 2.1 AA audit | D31: 10 | E31: 27 | F31: 46315 | G31: 46328 | H31: 46328 | I31: 30 | J31: 40 | K31: =IF(I31=0,"Yes","No") -> No | L31: =SUMIF(Assignments!$A:$A,A31,Assignments!$G:$G) -> 11000 | M31: 0 | N31: =L31+M31 -> 11000 | O31: =IF(N31=0,0,Q31/N31) -> 0 | P31: 0 | Q31: 0 | R31: =N31*P31 -> 0 | S31: 0 | T31: UX Designer
A32: 5.4 | B32: 5 | C32: Load testing (enrolment peak) | D32: 10 | E32: 28 | F32: 46336 | G32: 46349 | H32: 46363 | I32: 15 | J32: 15 | K32: =IF(I32=0,"Yes","No") -> No | L32: =SUMIF(Assignments!$A:$A,A32,Assignments!$G:$G) -> 9800 | M32: 0 | N32: =L32+M32 -> 9800 | O32: =IF(N32=0,0,Q32/N32) -> 0 | P32: 0 | Q32: 0 | R32: =N32*P32 -> 0 | S32: 0 | T32: Solution Architect
A33: 5.5 | B33: 5 | C33: User acceptance testing | D33: 15 | E33: 29 | F33: 46350 | G33: 46370 | H33: 46393 | I33: 0 | J33: 0 | K33: =IF(I33=0,"Yes","No") -> Yes | L33: =SUMIF(Assignments!$A:$A,A33,Assignments!$G:$G) -> 27000 | M33: 0 | N33: =L33+M33 -> 27000 | O33: =IF(N33=0,0,Q33/N33) -> 0 | P33: 0 | Q33: 0 | R33: =N33*P33 -> 0 | S33: 0 | T33: Test Lead
A34: 5.6 | B34: 5 | C34: Regression & defect remediation | D34: 8 | E34: 30 | F34: 46357 | G34: 46366 | H34: 46391 | I34: 2 | J34: 2 | K34: =IF(I34=0,"Yes","No") -> No | L34: =SUMIF(Assignments!$A:$A,A34,Assignments!$G:$G) -> 16160 | M34: 0 | N34: =L34+M34 -> 16160 | O34: =IF(N34=0,0,Q34/N34) -> 0 | P34: 0 | Q34: 0 | R34: =N34*P34 -> 0 | S34: 0 | T34: Test Lead
A35: M5 | B35: 5 | C35: UAT sign-off | D35: 0 | E35: 31 | F35: 46371 | G35: 46370 | H35: 46393 | I35: 0 | J35: 0 | K35: =IF(I35=0,"Yes","No") -> Yes | L35: =SUMIF(Assignments!$A:$A,A35,Assignments!$G:$G) -> 0 | M35: 0 | N35: =L35+M35 -> 0 | O35: =IF(N35=0,0,Q35/N35) -> 0 | P35: 0 | Q35: 0 | R35: =N35*P35 -> 0 | S35: 0 | T35: Project Manager
A36: 6.1 | B36: 6 | C36: Training & change comms | D36: 20 | E36: 32 | F36: 46322 | G36: 46349 | H36: 46349 | I36: 30 | J36: 40 | K36: =IF(I36=0,"Yes","No") -> No | L36: =SUMIF(Assignments!$A:$A,A36,Assignments!$G:$G) -> 14400 | M36: 8000 | N36: =L36+M36 -> 22400 | O36: =IF(N36=0,0,Q36/N36) -> 0 | P36: 0 | Q36: 0 | R36: =N36*P36 -> 0 | S36: 0 | T36: Project Manager
... A41: 6.5 | B41: 6 | C41: Legacy portal decommissioning | D41: 10 | E41: 37 | F41: 46437 | G41: 46450 | H41: 46464 | I41: 0 | J41: 0 | K41: =IF(I41=0,"Yes","No") -> Yes | L41: =SUMIF(Assignments!$A:$A,A41,Assignments!$G:$G) -> 10000 | M41: 0 | N41: =L41+M41 -> 10000 | O41: =IF(N41=0,0,Q41/N41) -> 0 | P41: 0 | Q41: 0 | R41: =N41*P41 -> 0 | S41: 0 | T41: Project Manager
C42: Totals (BAC / PV / EV / AC) | L42: =SUM(L5:L41) -> 651180 | M42: =SUM(M5:M41) -> 249000 | N42: =SUM(N5:N41) -> 900180 | Q42: =SUM(Q5:Q41) -> 242800 | R42: =SUM(R5:R41) -> 221830 | S42: =SUM(S5:S41) -> 231730
C44: Amber rows = behind plan at the status date (% complete < planned %). PV/EV/AC equal ProjectLibre BCWS/BCWP/ACWP per task.

Sheet Assignments
A1: Resource assignments (from the ProjectLibre plan)
A2: UniConnect — Student Portal Consolidation | Status date 25/09/2026 | Source: data/project.yaml
A4: WBS | B4: Role | C4: Units | D4: Baseline duration (d) | E4: Hours | F4: Rate | G4: Labour cost
A5: 1.1 | B5: Project Manager | C5: 1 | D5: =VLOOKUP(A5,Schedule_WBS!$A:$D,4,FALSE()) -> 10 | E5: =C5*D5*8 -> 80 | F5: =VLOOKUP(B5,Resources!$A:$C,3,FALSE()) -> 120 | G5: =E5*F5 -> 9600
A6: 1.1 | B6: Business Analyst | C6: 0.5 | D6: =VLOOKUP(A6,Schedule_WBS!$A:$D,4,FALSE()) -> 10 | E6: =C6*D6*8 -> 40 | F6: =VLOOKUP(B6,Resources!$A:$C,3,FALSE()) -> 95 | G6: =E6*F6 -> 3800
A7: 1.2 | B7: Project Manager | C7: 1 | D7: =VLOOKUP(A7,Schedule_WBS!$A:$D,4,FALSE()) -> 8 | E7: =C7*D7*8 -> 64 | F7: =VLOOKUP(B7,Resources!$A:$C,3,FALSE()) -> 120 | G7: =E7*F7 -> 7680
A8: 1.2 | B8: Business Analyst | C8: 0.5 | D8: =VLOOKUP(A8,Schedule_WBS!$A:$D,4,FALSE()) -> 8 | E8: =C8*D8*8 -> 32 | F8: =VLOOKUP(B8,Resources!$A:$C,3,FALSE()) -> 95 | G8: =E8*F8 -> 3040
A9: 1.2 | B9: Solution Architect | C9: 0.25 | D9: =VLOOKUP(A9,Schedule_WBS!$A:$D,4,FALSE()) -> 8 | E9: =C9*D9*8 -> 16 | F9: =VLOOKUP(B9,Resources!$A:$C,3,FALSE()) -> 140 | G9: =E9*F9 -> 2240
A10: 1.3 | B10: Project Manager | C10: 0.5 | D10: =VLOOKUP(A10,Schedule_WBS!$A:$D,4,FALSE()) -> 138 | E10: =C10*D10*8 -> 552 | F10: =VLOOKUP(B10,Resources!$A:$C,3,FALSE()) -> 120 | G10: =E10*F10 -> 66240
A11: 1.3 | B11: Business Analyst | C11: 0.25 | D11: =VLOOKUP(A11,Schedule_WBS!$A:$D,4,FALSE()) -> 138 | E11: =C11*D11*8 -> 276 | F11: =VLOOKUP(B11,Resources!$A:$C,3,FALSE()) -> 95 | G11: =E11*F11 -> 26220
A12: 1.4 | B12: Project Manager | C12: 1 | D12: =VLOOKUP(A12,Schedule_WBS!$A:$D,4,FALSE()) -> 5 | E12: =C12*D12*8 -> 40 | F12: =VLOOKUP(B12,Resources!$A:$C,3,FALSE()) -> 120 | G12: =E12*F12 -> 4800
A13: 1.4 | B13: Business Analyst | C13: 0.5 | D13: =VLOOKUP(A13,Schedule_WBS!$A:$D,4,FALSE()) -> 5 | E13: =C13*D13*8 -> 20 | F13: =VLOOKUP(B13,Resources!$A:$C,3,FALSE()) -> 95 | G13: =E13*F13 -> 1900
A14: 2.1 | B14: Business Analyst | C14: 1 | D14: =VLOOKUP(A14,Schedule_WBS!$A:$D,4,FALSE()) -> 10 | E14: =C14*D14*8 -> 80 | F14: =VLOOKUP(B14,Resources!$A:$C,3,FALSE()) -> 95 | G14: =E14*F14 -> 7600
A15: 2.1 | B15: Data Engineer | C15: 0.5 | D15: =VLOOKUP(A15,Schedule_WBS!$A:$D,4,FALSE()) -> 10 | E15: =C15*D15*8 -> 40 | F15: =VLOOKUP(B15,Resources!$A:$C,3,FALSE()) -> 110 | G15: =E15*F15 -> 4400
A16: 2.1 | B16: Solution Architect | C16: 0.25 | D16: =VLOOKUP(A16,Schedule_WBS!$A:$D,4,FALSE()) -> 10 | E16: =C16*D16*8 -> 20 | F16: =VLOOKUP(B16,Resources!$A:$C,3,FALSE()) -> 140 | G16: =E16*F16 -> 2800
... A84: 6.5 | B84: Data Engineer | C84: 0.5 | D84: =VLOOKUP(A84,Schedule_WBS!$A:$D,4,FALSE()) -> 10 | E84: =C84*D84*8 -> 40 | F84: =VLOOKUP(B84,Resources!$A:$C,3,FALSE()) -> 110 | G84: =E84*F84 -> 4400

Sheet Resources
A1: Resources and rates (AUD)
A2: UniConnect — Student Portal Consolidation | Status date 25/09/2026 | Source: data/project.yaml
A4: Role | B4: Count (FTE) | C4: Rate per hour | D4: Type | E4: Baseline hours | F4: Baseline labour cost
A5: Project Manager | B5: 1 | C5: 120 | D5: Work | E5: =SUMIF(Assignments!$B:$B,A5,Assignments!$E:$E) -> 776 | F5: =SUMIF(Assignments!$B:$B,A5,Assignments!$G:$G) -> 93120
A6: Business Analyst | B6: 1 | C6: 95 | D6: Work | E6: =SUMIF(Assignments!$B:$B,A6,Assignments!$E:$E) -> 928 | F6: =SUMIF(Assignments!$B:$B,A6,Assignments!$G:$G) -> 88160
A7: Solution Architect | B7: 1 | C7: 140 | D7: Work | E7: =SUMIF(Assignments!$B:$B,A7,Assignments!$E:$E) -> 336 | F7: =SUMIF(Assignments!$B:$B,A7,Assignments!$G:$G) -> 47040
A8: Developer | B8: 3 | C8: 105 | D8: Work | E8: =SUMIF(Assignments!$B:$B,A8,Assignments!$E:$E) -> 1848 | F8: =SUMIF(Assignments!$B:$B,A8,Assignments!$G:$G) -> 194040
A9: Data Engineer | B9: 1 | C9: 110 | D9: Work | E9: =SUMIF(Assignments!$B:$B,A9,Assignments!$E:$E) -> 500 | F9: =SUMIF(Assignments!$B:$B,A9,Assignments!$G:$G) -> 55000
A10: Tester | B10: 2 | C10: 85 | D10: Work | E10: =SUMIF(Assignments!$B:$B,A10,Assignments!$E:$E) -> 932 | F10: =SUMIF(Assignments!$B:$B,A10,Assignments!$G:$G) -> 79220
A11: UX Designer | B11: 1 | C11: 95 | D11: Work | E11: =SUMIF(Assignments!$B:$B,A11,Assignments!$E:$E) -> 400 | F11: =SUMIF(Assignments!$B:$B,A11,Assignments!$G:$G) -> 38000
A12: Change & Training Lead | B12: 1 | C12: 90 | D12: Work | E12: =SUMIF(Assignments!$B:$B,A12,Assignments!$E:$E) -> 380 | F12: =SUMIF(Assignments!$B:$B,A12,Assignments!$G:$G) -> 34200
A13: Security Consultant | B13: 1 | C13: 160 | D13: Work (contract) | E13: =SUMIF(Assignments!$B:$B,A13,Assignments!$E:$E) -> 140 | F13: =SUMIF(Assignments!$B:$B,A13,Assignments!$G:$G) -> 22400
A14: Total | E14: =SUM(E5:E13) -> 6240 | F14: =SUM(F5:F13) -> 651180

Sheet Lookups
A1: Lookups & scoring scales
A2: UniConnect — Student Portal Consolidation | Status date 25/09/2026 | Source: data/project.yaml
A4: Likelihood | B4: Label | C4: Band | D4: Probability | G4: Strategy | H4: Status | I4: CCB decision | J4: RAG | K4: RACI | M4: Holidays (NSW + SCU shutdown)
A5: 1 | B5: Rare | C5: < 10% | D5: 0.05 | G5: Avoid | H5: Open | I5: Approved | J5: Green | K5: R | M5: 46300 | N5: Labour Day (NSW)
A6: 2 | B6: Unlikely | C6: 10–30% | D6: 0.15 | G6: Mitigate | H6: In progress | I6: Deferred | J6: Amber | K6: A | M6: 46380 | N6: University shutdown
A7: 3 | B7: Possible | C7: 30–50% | D7: 0.4 | G7: Transfer | H7: Closed | I7: Rejected | J7: Red | K7: C | M7: 46381 | N7: Christmas Day
A8: 4 | B8: Likely | C8: 50–80% | D8: 0.65 | G8: Accept | H8: Not started | I8: Pending | J8: Grey | K8: I | M8: 46384 | N8: Boxing Day (observed)
A9: 5 | B9: Almost certain | C9: > 80% | D9: 0.9 | G9: Exploit | H9: Done | M9: 46385 | N9: University shutdown
G10: Enhance | M10: 46386 | N10: University shutdown
A11: Impact | B11: Label | C11: Cost | D11: Schedule | E11: Other | G11: Share | M11: 46387 | N11: University shutdown
A12: 1 | B12: Insignificant | C12: < $5k | D12: < 2 days | E12: No external visibility | M12: 46388 | N12: New Year's Day
A13: 2 | B13: Minor | C13: $5k–15k | D13: 2–5 days | E13: Internal complaints | M13: 46413 | N13: Australia Day
A14: 3 | B14: Moderate | C14: $15k–40k | D14: 1–2 weeks | E14: Student complaints; SRC attention | M14: 46472 | N14: Good Friday
A15: 4 | B15: Major | C15: $40k–100k | D15: 2–4 weeks; milestone missed | E15: Media/regulator enquiry | M15: 46475 | N15: Easter Monday
A16: 5 | B16: Severe | C16: > $100k | D16: > 4 weeks; go-live deadline missed | E16: Notifiable data breach; TEQSA action
A18: Rating | B18: Min score | C18: Max score | D18: Colour
A19: Low | B19: 1 | C19: 4 | D19: green
A20: Medium | B20: 5 | C20: 9 | D20: yellow
A21: High | B21: 10 | C21: 16 | D21: orange
A22: Extreme | B22: 20 | C22: 25 | D22: red
